[
{"geohash": "sxk6sr","value": 71},
{"geohash": "sxkb7x","value": 38},
{"geohash": "sxkbgw","value": 86},
{"geohash": "sxkdj1","value": 26},
{"geohash": "sxk9cf","value": 18},
{"geohash": "sxkbb1","value": 39},
{"geohash": "sx7fv7","value": 45},
{"geohash": "sxk9w0","value": 27},
{"geohash": "sxkb8c","value": 44},
{"geohash": "sxkdre","value": 107},
{"geohash": "sxk6g5","value": 80},
{"geohash": "sxk1fc","value": 62},
{"geohash": "sx7ftz","value": 66},
{"geohash": "sxk9dv","value": 35},
{"geohash": "sxk9s1","value": 27},
{"geohash": "sxk68d","value": 87},
{"geohash": "sxk1uc","value": 86},
{"geohash": "sx7ck9","value": 65},
{"geohash": "sxk18n","value": 86},
{"geohash": "sxk1fp","value": 73},
{"geohash": "sxk92h","value": 15},
{"geohash": "sx7fr9","value": 87},
{"geohash": "sxk1ff","value": 66},
{"geohash": "sxkc0q","value": 22},
{"geohash": "sxk3qf","value": 42},
{"geohash": "sxk35q","value": 11},
{"geohash": "sxk3z4","value": 35},
{"geohash": "sxkc0d","value": 64},
{"geohash": "sxk1uf","value": 112},
{"geohash": "sxkd31","value": 64},
{"geohash": "sxkbdj","value": 31},
{"geohash": "sx7cw9","value": 90},
{"geohash": "sxk92t","value": 15},
{"geohash": "sxk9e4","value": 48},
{"geohash": "sxk1tu","value": 93},
{"geohash": "sxk9y7","value": 74},
{"geohash": "sxk9vj","value": 32},
{"geohash": "sxk8xz","value": 20},
{"geohash": "sxk96s","value": 20},
{"geohash": "sxkdtb","value": 92},
{"geohash": "sxk9qn","value": 21},
{"geohash": "sxk3ze","value": 98},
{"geohash": "sxk97r","value": 22},
{"geohash": "sxkd2p","value": 93},
{"geohash": "sxk600","value": 95},
{"geohash": "sxk9pr","value": 18},
{"geohash": "sxk9ge","value": 32},
{"geohash": "sxkbsp","value": 58},
{"geohash": "sxkdh5","value": 59},
{"geohash": "sxkbsd","value": 78},
{"geohash": "sx7chm","value": 66},
{"geohash": "sxk8z8","value": 21},
{"geohash": "sxkc41","value": 48},
{"geohash": "sxkbhd","value": 80},
{"geohash": "sxk9k3","value": 35},
{"geohash": "sxkc58","value": 74},
{"geohash": "sxkd30","value": 77},
{"geohash": "sxkcub","value": 84},
{"geohash": "sxk9js","value": 20},
{"geohash": "sxk92e","value": 14},
{"geohash": "sxk9f0","value": 28},
{"geohash": "sxkc0p","value": 26},
{"geohash": "sxk94j","value": 70},
{"geohash": "sxk45b","value": 51},
{"geohash": "sxk1ft","value": 103},
{"geohash": "sxkb9v","value": 26},
{"geohash": "sxk6x0","value": 67},
{"geohash": "sxkc61","value": 93},
{"geohash": "sxk9g3","value": 29},
{"geohash": "sxk9kd","value": 21},
{"geohash": "sxk4py","value": 70},
{"geohash": "sxk99q","value": 20},
{"geohash": "sxkbeu","value": 29},
{"geohash": "sxkd2s","value": 94},
{"geohash": "sxkbu0","value": 44},
{"geohash": "sxk1ch","value": 77},
{"geohash": "sxk9tz","value": 20},
{"geohash": "sxkb9f","value": 27},
{"geohash": "sxkds9","value": 85},
{"geohash": "sxk9kf","value": 15},
{"geohash": "sxk18r","value": 85},
{"geohash": "sxk9m5","value": 29},
{"geohash": "sxkc31","value": 28},
{"geohash": "sxk3g3","value": 83},
{"geohash": "sxkb8v","value": 25},
{"geohash": "sxkdn8","value": 58},
{"geohash": "sxk8xy","value": 24},
{"geohash": "sxkc0m","value": 57},
{"geohash": "sxk4hg","value": 94},
{"geohash": "sxk3sc","value": 34},
{"geohash": "sxk9u9","value": 39},
{"geohash": "sx7ctx","value": 72},
{"geohash": "sxk6df","value": 26},
{"geohash": "sxk9rf","value": 24},
{"geohash": "sxk6rv","value": 86},
{"geohash": "sxk3rn","value": 20},
{"geohash": "sxk6wk","value": 89},
{"geohash": "sxkbjd","value": 79},
{"geohash": "sxk9n2","value": 24},
{"geohash": "sx7czd","value": 70},
{"geohash": "sxk9gb","value": 13},
{"geohash": "sxk6tu","value": 88},
{"geohash": "sxk3be","value": 72},
{"geohash": "sxkd2g","value": 86},
{"geohash": "sxk9xc","value": 98},
{"geohash": "sxk8xp","value": 34},
{"geohash": "sxk97y","value": 18},
{"geohash": "sxk9t3","value": 23},
{"geohash": "sx7fpz","value": 89},
{"geohash": "sxk3ng","value": 32},
{"geohash": "sxk3x6","value": 20},
{"geohash": "sxkb8n","value": 19},
{"geohash": "sxkdj2","value": 39},
{"geohash": "sxkb95","value": 18},
{"geohash": "sxk99u","value": 22},
{"geohash": "sxk9j5","value": 19},
{"geohash": "sxk3w5","value": 28},
{"geohash": "sxk6wu","value": 86},
{"geohash": "sxkdhu","value": 41},
{"geohash": "sxk3pp","value": 17},
{"geohash": "sxk98e","value": 35},
{"geohash": "sxk408","value": 97},
{"geohash": "sxk3wz","value": 70},
{"geohash": "sxkc26","value": 46},
{"geohash": "sxk979","value": 65},
{"geohash": "sxkd7f","value": 51},
{"geohash": "sxk3rm","value": 19},
{"geohash": "sxkbhj","value": 52},
{"geohash": "sxkbbe","value": 58},
{"geohash": "sxk1tr","value": 84},
{"geohash": "sxkc1k","value": 43},
{"geohash": "sxk6xk","value": 40},
{"geohash": "sxk9ts","value": 24},
{"geohash": "sxk6dx","value": 84},
{"geohash": "sxk6rf","value": 92},
{"geohash": "sxk8zz","value": 37},
{"geohash": "sxk4ps","value": 71},
{"geohash": "sxk3x4","value": 18},
{"geohash": "sxk8xs","value": 36},
{"geohash": "sxkb74","value": 56},
{"geohash": "sxk8yt","value": 20},
{"geohash": "sx7fqv","value": 75},
{"geohash": "sxkcgj","value": 61},
{"geohash": "sxk6p4","value": 45},
{"geohash": "sxkddd","value": 108},
{"geohash": "sxkfpx","value": 99},
{"geohash": "sxkbd0","value": 26},
{"geohash": "sxk37f","value": 35},
{"geohash": "sxk3bd","value": 88},
{"geohash": "sxk93x","value": 46},
{"geohash": "sxk9jy","value": 19},
{"geohash": "sxk3gq","value": 44},
{"geohash": "sxk96z","value": 19},
{"geohash": "sxk3bf","value": 90},
{"geohash": "sxkd1p","value": 79},
{"geohash": "sxk6u4","value": 82},
{"geohash": "sxk9e3","value": 25},
{"geohash": "sxk9de","value": 27},
{"geohash": "sxk8z2","value": 26},
{"geohash": "sxk326","value": 77},
{"geohash": "sxk9bj","value": 96},
{"geohash": "sxk3td","value": 28},
{"geohash": "sxk9e8","value": 26},
{"geohash": "sxk18t","value": 82},
{"geohash": "sxk9w3","value": 37},
{"geohash": "sxk9d3","value": 21},
{"geohash": "sxk96p","value": 19},
{"geohash": "sxk9dd","value": 30},
{"geohash": "sxk6q7","value": 31},
{"geohash": "sxkbm8","value": 86},
{"geohash": "sxkf2g","value": 60},
{"geohash": "sxk3w0","value": 51},
{"geohash": "sxk6xc","value": 78},
{"geohash": "sxkber","value": 63},
{"geohash": "sx7cmz","value": 85},
{"geohash": "sxk3k8","value": 40},
{"geohash": "sxkdkf","value": 31},
{"geohash": "sxk9jf","value": 19},
{"geohash": "sxkd5u","value": 54},
{"geohash": "sxk991","value": 19},
{"geohash": "sxk6st","value": 64},
{"geohash": "sxk9sm","value": 29},
{"geohash": "sxk9eb","value": 18},
{"geohash": "sxkbhk","value": 80},
{"geohash": "sx7fqu","value": 62},
{"geohash": "sxk9uk","value": 29},
{"geohash": "sxk9hk","value": 15},
{"geohash": "sxkd4d","value": 33},
{"geohash": "sxkcd1","value": 98},
{"geohash": "sxk3s9","value": 50},
{"geohash": "sxk3hf","value": 45},
{"geohash": "sxkc6p","value": 68},
{"geohash": "sxk9d1","value": 17},
{"geohash": "sxk8z9","value": 38},
{"geohash": "sxk90x","value": 16},
{"geohash": "sxk91n","value": 17},
{"geohash": "sxk9eh","value": 34},
{"geohash": "sxk998","value": 19},
{"geohash": "sxkcer","value": 62},
{"geohash": "sxk6rb","value": 132},
{"geohash": "sxk8yv","value": 24},
{"geohash": "sxk386","value": 100},
{"geohash": "sxk9es","value": 21},
{"geohash": "sxk33v","value": 53},
{"geohash": "sxkc3v","value": 43},
{"geohash": "sxk3xt","value": 62},
{"geohash": "sxk9j1","value": 35},
{"geohash": "sxkc2c","value": 21},
{"geohash": "sxkbgc","value": 40},
{"geohash": "sx7fwj","value": 81},
{"geohash": "sxkc0z","value": 28},
{"geohash": "sxkd1v","value": 39},
{"geohash": "sx7cxt","value": 71},
{"geohash": "sxk456","value": 90},
{"geohash": "sxk9ve","value": 39},
{"geohash": "sxk9g6","value": 45},
{"geohash": "sxk8z5","value": 32},
{"geohash": "sxkc3k","value": 50},
{"geohash": "sxk3he","value": 26},
{"geohash": "sxk929","value": 16},
{"geohash": "sxk392","value": 92},
{"geohash": "sxk9se","value": 29},
{"geohash": "sxkc2k","value": 89},
{"geohash": "sxk3n5","value": 31},
{"geohash": "sxkc90","value": 111},
{"geohash": "sxk9qh","value": 19},
{"geohash": "sxkc50","value": 77},
{"geohash": "sxk9pk","value": 23},
{"geohash": "sxkc28","value": 21},
{"geohash": "sxk6pb","value": 44},
{"geohash": "sxk3rf","value": 17},
{"geohash": "sxk395","value": 82},
{"geohash": "sxk93s","value": 38},
{"geohash": "sxk9nq","value": 33},
{"geohash": "sxk1x3","value": 97},
{"geohash": "sxk3wt","value": 34},
{"geohash": "sxk3eg","value": 47},
{"geohash": "sxk18v","value": 71},
{"geohash": "sxk3x5","value": 28},
{"geohash": "sxk66q","value": 87},
{"geohash": "sxk37q","value": 34},
{"geohash": "sxk1u4","value": 84},
{"geohash": "sxkds3","value": 81},
{"geohash": "sxkb76","value": 55},
{"geohash": "sxk66y","value": 62},
{"geohash": "sxk9u1","value": 42},
{"geohash": "sxkc05","value": 27},
{"geohash": "sxkf1u","value": 95},
{"geohash": "sxk4pc","value": 53},
{"geohash": "sxkdky","value": 39},
{"geohash": "sxm40v","value": 48},
{"geohash": "sxk3hs","value": 59},
{"geohash": "sxk9zj","value": 45},
{"geohash": "sxk8zs","value": 28},
{"geohash": "sxk9kw","value": 22},
{"geohash": "sxk1fr","value": 85},
{"geohash": "sxk9nx","value": 31},
{"geohash": "sxkd8c","value": 97},
{"geohash": "sxk907","value": 64},
{"geohash": "sxkb6p","value": 32},
{"geohash": "sxk9et","value": 13},
{"geohash": "sxkfp4","value": 104},
{"geohash": "sxkdh3","value": 17},
{"geohash": "sxkdd4","value": 100},
{"geohash": "sxk399","value": 63},
{"geohash": "sxkdd3","value": 95},
{"geohash": "sxkb8h","value": 21},
{"geohash": "sxk9sb","value": 10},
{"geohash": "sxk974","value": 11},
{"geohash": "sx7cht","value": 32},
{"geohash": "sxkdhs","value": 27},
{"geohash": "sxk93e","value": 25},
{"geohash": "sxk9t8","value": 20},
{"geohash": "sxk18p","value": 93},
{"geohash": "sxk9kk","value": 20},
{"geohash": "sxkdpg","value": 74},
{"geohash": "sxk9ue","value": 24},
{"geohash": "sxk6kd","value": 47},
{"geohash": "sxk396","value": 57},
{"geohash": "sxk3gs","value": 43},
{"geohash": "sx7cm5","value": 72},
{"geohash": "sxkdhz","value": 44},
{"geohash": "sxk3re","value": 39},
{"geohash": "sx7fw4","value": 82},
{"geohash": "sxk9ep","value": 29},
{"geohash": "sxk3nh","value": 32},
{"geohash": "sxk98f","value": 25},
{"geohash": "sxk3xx","value": 78},
{"geohash": "sxk993","value": 40},
{"geohash": "sxk3e6","value": 25},
{"geohash": "sxkds8","value": 79},
{"geohash": "sx7cx7","value": 84},
{"geohash": "sxkde4","value": 96},
{"geohash": "sx7fmn","value": 89},
{"geohash": "sxk4h3","value": 92},
{"geohash": "sxkb86","value": 59},
{"geohash": "sxk1w1","value": 76},
{"geohash": "sxkf22","value": 69},
{"geohash": "sxk9ee","value": 18},
{"geohash": "sxkc2z","value": 107},
{"geohash": "sxk8xu","value": 42},
{"geohash": "sxk9ur","value": 40},
{"geohash": "sxk6eu","value": 100},
{"geohash": "sxkbg9","value": 55},
{"geohash": "sxk9w1","value": 28},
{"geohash": "sxkdkg","value": 41},
{"geohash": "sxk3xu","value": 52},
{"geohash": "sxkcdg","value": 82},
{"geohash": "sxk3bt","value": 91},
{"geohash": "sxkb99","value": 18},
{"geohash": "sxk3qy","value": 22},
{"geohash": "sxk9nc","value": 26},
{"geohash": "sxk9ns","value": 20},
{"geohash": "sxkbbx","value": 27},
{"geohash": "sxk9b9","value": 65},
{"geohash": "sxk9sd","value": 35},
{"geohash": "sxk4pz","value": 75},
{"geohash": "sxkcu8","value": 77},
{"geohash": "sxkceq","value": 71},
{"geohash": "sxk9t9","value": 20},
{"geohash": "sxk9d0","value": 16},
{"geohash": "sxk9tc","value": 33},
{"geohash": "sxk9e2","value": 18},
{"geohash": "sxkd87","value": 75},
{"geohash": "sxk9n4","value": 24},
{"geohash": "sxk92z","value": 16},
{"geohash": "sxk6mf","value": 25},
{"geohash": "sxk9ux","value": 29},
{"geohash": "sxk4pf","value": 76},
{"geohash": "sxk3kt","value": 19},
{"geohash": "sxk3sh","value": 31},
{"geohash": "sxkc33","value": 31},
{"geohash": "sxk9rj","value": 42},
{"geohash": "sxkc2x","value": 107},
{"geohash": "sxk994","value": 40},
{"geohash": "sxk1xf","value": 98},
{"geohash": "sxk9je","value": 16},
{"geohash": "sxk968","value": 65},
{"geohash": "sxk9ku","value": 24},
{"geohash": "sxk1ej","value": 70},
{"geohash": "sxk8ym","value": 42},
{"geohash": "sxk4r9","value": 84},
{"geohash": "sxkc6h","value": 89},
{"geohash": "sxk3ew","value": 81},
{"geohash": "sxk964","value": 25},
{"geohash": "sx7cw0","value": 52},
{"geohash": "sxkf29","value": 85},
{"geohash": "sxk3x0","value": 31},
{"geohash": "sxk98h","value": 52},
{"geohash": "sxkb90","value": 52},
{"geohash": "sxk6p2","value": 92},
{"geohash": "sxk19q","value": 82},
{"geohash": "sxk3e3","value": 24},
{"geohash": "sx7ghm","value": 68},
{"geohash": "sxk91t","value": 21},
{"geohash": "sxk9ez","value": 20},
{"geohash": "sxk3jn","value": 23},
{"geohash": "sxk92p","value": 18},
{"geohash": "sxkbsj","value": 45},
{"geohash": "sxk3zw","value": 97},
{"geohash": "sxk1ge","value": 95},
{"geohash": "sxk6pd","value": 89},
{"geohash": "sxkd49","value": 43},
{"geohash": "sxk91p","value": 51},
{"geohash": "sxk9bs","value": 23},
{"geohash": "sxk3hz","value": 48},
{"geohash": "sxkfpy","value": 84},
{"geohash": "sx7cmm","value": 91},
{"geohash": "sxk3wg","value": 35},
{"geohash": "sxk9tq","value": 23},
{"geohash": "sxk1b8","value": 125},
{"geohash": "sxkfn9","value": 99},
{"geohash": "sxkbue","value": 113},
{"geohash": "sxk9tm","value": 22},
{"geohash": "sxkc52","value": 64},
{"geohash": "sxk1g5","value": 54},
{"geohash": "sxk9mz","value": 26},
{"geohash": "sxk9dx","value": 26},
{"geohash": "sxkbev","value": 30},
{"geohash": "sxkdqn","value": 109},
{"geohash": "sxk9uv","value": 39},
{"geohash": "sxk9t4","value": 39},
{"geohash": "sxk1v3","value": 105},
{"geohash": "sxk9j8","value": 35},
{"geohash": "sxkbu5","value": 49},
{"geohash": "sxk6x6","value": 72},
{"geohash": "sxk333","value": 61},
{"geohash": "sxk98c","value": 25},
{"geohash": "sx7cw3","value": 93},
{"geohash": "sxkds0","value": 103},
{"geohash": "sxk1dx","value": 45},
{"geohash": "sxkc2b","value": 19},
{"geohash": "sxkd86","value": 85},
{"geohash": "sxk8z0","value": 23},
{"geohash": "sxk9s7","value": 25},
{"geohash": "sxk1gh","value": 85},
{"geohash": "sxkcfm","value": 88},
{"geohash": "sxkd79","value": 29},
{"geohash": "sx7ghd","value": 23},
{"geohash": "sxk3g4","value": 85},
{"geohash": "sxk3ns","value": 35},
{"geohash": "sxk93h","value": 19},
{"geohash": "sxkbbv","value": 48},
{"geohash": "sxk6sh","value": 97},
{"geohash": "sxk9c1","value": 20},
{"geohash": "sxk9u4","value": 45},
{"geohash": "sx7fp8","value": 53},
{"geohash": "sxkbhe","value": 62},
{"geohash": "sxk3px","value": 65},
{"geohash": "sxk9jz","value": 20},
{"geohash": "sxk3se","value": 25},
{"geohash": "sxkd4b","value": 44},
{"geohash": "sxkb7z","value": 41},
{"geohash": "sxk9gg","value": 28},
{"geohash": "sxk36k","value": 61},
{"geohash": "sxkd1r","value": 40},
{"geohash": "sxk8zj","value": 31},
{"geohash": "sxk3w3","value": 36},
{"geohash": "sxk3rj","value": 23},
{"geohash": "sxk3hw","value": 60},
{"geohash": "sxk9py","value": 39},
{"geohash": "sxkbf8","value": 17},
{"geohash": "sxk96m","value": 31},
{"geohash": "sxkf1v","value": 92},
{"geohash": "sxk9wc","value": 25},
{"geohash": "sxk9nw","value": 32},
{"geohash": "sxk9sf","value": 26},
{"geohash": "sxkdh7","value": 55},
{"geohash": "sxk9ye","value": 61},
{"geohash": "sxk3q9","value": 29},
{"geohash": "sx7fme","value": 87},
{"geohash": "sxk655","value": 25},
{"geohash": "sxk9te","value": 29},
{"geohash": "sxk93t","value": 30},
{"geohash": "sxk1dv","value": 53},
{"geohash": "sxkfnc","value": 75},
{"geohash": "sxk3s3","value": 47},
{"geohash": "sxk3c7","value": 87},
{"geohash": "sxk653","value": 60},
{"geohash": "sxkd1w","value": 43},
{"geohash": "sxk9m1","value": 18},
{"geohash": "sxk40n","value": 92},
{"geohash": "sxk9ec","value": 22},
{"geohash": "sxkc01","value": 68},
{"geohash": "sxkc64","value": 93},
{"geohash": "sxkc38","value": 32},
{"geohash": "sxk32c","value": 71},
{"geohash": "sxk6nv","value": 50},
{"geohash": "sxk367","value": 53},
{"geohash": "sxk6qh","value": 30},
{"geohash": "sxkb5r","value": 43},
{"geohash": "sxm44k","value": 49},
{"geohash": "sxk652","value": 53},
{"geohash": "sxk9x0","value": 66},
{"geohash": "sx7cu9","value": 80},
{"geohash": "sxkc07","value": 29},
{"geohash": "sxk6sz","value": 43},
{"geohash": "sxk6u2","value": 70},
{"geohash": "sxk9tp","value": 33},
{"geohash": "sxkd80","value": 82},
{"geohash": "sxm40q","value": 73},
{"geohash": "sxk3rw","value": 38},
{"geohash": "sxk9dn","value": 19},
{"geohash": "sxkc00","value": 86},
{"geohash": "sxk3zh","value": 25},
{"geohash": "sxkfnd","value": 61},
{"geohash": "sxk3t7","value": 26},
{"geohash": "sxkb7h","value": 70},
{"geohash": "sxk93c","value": 23},
{"geohash": "sxk3nt","value": 36},
{"geohash": "sxkb8y","value": 36},
{"geohash": "sxkbk7","value": 94},
{"geohash": "sxkbug","value": 117},
{"geohash": "sxkb5z","value": 51},
{"geohash": "sxk97d","value": 49},
{"geohash": "sxhzvw","value": 44},
{"geohash": "sxkd2c","value": 84},
{"geohash": "sxk3ny","value": 16},
{"geohash": "sxk9kv","value": 28},
{"geohash": "sxk3qb","value": 22},
{"geohash": "sxkdjp","value": 22},
{"geohash": "sxkbmj","value": 91},
{"geohash": "sx7cwf","value": 85},
{"geohash": "sxkcfd","value": 96},
{"geohash": "sxk1qy","value": 68},
{"geohash": "sxkd8f","value": 96},
{"geohash": "sxk3wb","value": 26},
{"geohash": "sxkd82","value": 98},
{"geohash": "sxkbbf","value": 22},
{"geohash": "sxk3pu","value": 49},
{"geohash": "sxkdkp","value": 86},
{"geohash": "sxkbgr","value": 72},
{"geohash": "sxk448","value": 97},
{"geohash": "sxk4px","value": 79},
{"geohash": "sxk9us","value": 33},
{"geohash": "sxk1t6","value": 56},
{"geohash": "sxkf43","value": 97},
{"geohash": "sxk90n","value": 31},
{"geohash": "sxk9ed","value": 19},
{"geohash": "sxkc0e","value": 45},
{"geohash": "sxk8xx","value": 21},
{"geohash": "sxkd96","value": 96},
{"geohash": "sxk9nd","value": 19},
{"geohash": "sxkbdn","value": 38},
{"geohash": "sxkc6j","value": 68},
{"geohash": "sxkb8w","value": 39},
{"geohash": "sxk9k4","value": 39},
{"geohash": "sxk9w9","value": 28},
{"geohash": "sxk96b","value": 45},
{"geohash": "sxk1td","value": 41},
{"geohash": "sxk3rg","value": 22},
{"geohash": "sxk9hw","value": 30},
{"geohash": "sxk3gr","value": 57},
{"geohash": "sxk39n","value": 79},
{"geohash": "sxk3p3","value": 43},
{"geohash": "sxk683","value": 81},
{"geohash": "sxk98g","value": 38},
{"geohash": "sxk37r","value": 32},
{"geohash": "sxkdkh","value": 53},
{"geohash": "sxk9wp","value": 35},
{"geohash": "sxk691","value": 79},
{"geohash": "sxkc4b","value": 46},
{"geohash": "sxk38w","value": 94},
{"geohash": "sxkd1g","value": 29},
{"geohash": "sxk99y","value": 19},
{"geohash": "sxk9sg","value": 35},
{"geohash": "sxkbmn","value": 91},
{"geohash": "sxk9wn","value": 40},
{"geohash": "sxk6sk","value": 93},
{"geohash": "sxk8zy","value": 38},
{"geohash": "sxk923","value": 18},
{"geohash": "sx7cxx","value": 70},
{"geohash": "sxkfp5","value": 78},
{"geohash": "sxk9dc","value": 24},
{"geohash": "sxkbhp","value": 75},
{"geohash": "sxk9km","value": 23},
{"geohash": "sx7cmh","value": 86},
{"geohash": "sxkcdj","value": 105},
{"geohash": "sxk9mv","value": 19},
{"geohash": "sxkc92","value": 109},
{"geohash": "sxkc0t","value": 41},
{"geohash": "sxk9ub","value": 73},
{"geohash": "sxkbe4","value": 76},
{"geohash": "sxk9fu","value": 55},
{"geohash": "sxkbhf","value": 78},
{"geohash": "sxk98m","value": 67},
{"geohash": "sxk9g9","value": 22},
{"geohash": "sxk3z3","value": 59},
{"geohash": "sxk9mw","value": 24},
{"geohash": "sxkd5v","value": 56},
{"geohash": "sxk6q1","value": 19},
{"geohash": "sxkcvz","value": 83},
{"geohash": "sxk8zg","value": 20},
{"geohash": "sxk92r","value": 21},
{"geohash": "sxkdd9","value": 102},
{"geohash": "sxk90h","value": 70},
{"geohash": "sxk98k","value": 75},
{"geohash": "sxk9en","value": 31},
{"geohash": "sxk3s2","value": 30},
{"geohash": "sxk9pt","value": 21},
{"geohash": "sxkc25","value": 38},
{"geohash": "sxk4re","value": 85},
{"geohash": "sxk9q4","value": 20},
{"geohash": "sxk9hm","value": 17},
{"geohash": "sxk963","value": 19},
{"geohash": "sxkdp3","value": 70},
{"geohash": "sxk9j3","value": 30},
{"geohash": "sxkbj9","value": 71},
{"geohash": "sxk3hx","value": 53},
{"geohash": "sxkbmh","value": 86},
{"geohash": "sx7fty","value": 73},
{"geohash": "sxk37h","value": 31},
{"geohash": "sxk9gs","value": 50},
{"geohash": "sxkfpq","value": 77},
{"geohash": "sxkbe5","value": 73},
{"geohash": "sx7cwd","value": 103},
{"geohash": "sxk9q6","value": 22},
{"geohash": "sxk9ej","value": 25},
{"geohash": "sxk60v","value": 95},
{"geohash": "sxkdm0","value": 21},
{"geohash": "sxk91h","value": 17},
{"geohash": "sxkbum","value": 45},
{"geohash": "sxk1cn","value": 97},
{"geohash": "sxk6p6","value": 46},
{"geohash": "sxkf1g","value": 110},
{"geohash": "sxk3r1","value": 18},
{"geohash": "sxk3qd","value": 47},
{"geohash": "sxk9n0","value": 22},
{"geohash": "sxk94n","value": 44},
{"geohash": "sxkdke","value": 32},
{"geohash": "sxk67d","value": 45},
{"geohash": "sxk9gc","value": 16},
{"geohash": "sxk3z6","value": 42},
{"geohash": "sx7cz8","value": 73},
{"geohash": "sxk9pc","value": 37},
{"geohash": "sxk92u","value": 20},
{"geohash": "sxk1tg","value": 82},
{"geohash": "sxk677","value": 60},
{"geohash": "sxk6qe","value": 27},
{"geohash": "sxk1wf","value": 95},
{"geohash": "sxk9pq","value": 21},
{"geohash": "sxkf0r","value": 59},
{"geohash": "sxkfnf","value": 109},
{"geohash": "sxk9p8","value": 46},
{"geohash": "sxk3rd","value": 35},
{"geohash": "sxkb8d","value": 56},
{"geohash": "sxk3f7","value": 92},
{"geohash": "sxk3eu","value": 92},
{"geohash": "sxkdhh","value": 51},
{"geohash": "sxk9v2","value": 60},
{"geohash": "sx7fvr","value": 33},
{"geohash": "sxk3kf","value": 29},
{"geohash": "sxkbfv","value": 28},
{"geohash": "sxk9uz","value": 37},
{"geohash": "sxkbey","value": 44},
{"geohash": "sxk8z3","value": 27},
{"geohash": "sxk4he","value": 103},
{"geohash": "sxk3nv","value": 39},
{"geohash": "sxkf8b","value": 19},
{"geohash": "sxkbj2","value": 51},
{"geohash": "sx7fkw","value": 93},
{"geohash": "sxk675","value": 51},
{"geohash": "sxk9uy","value": 33},
{"geohash": "sxk9n8","value": 27},
{"geohash": "sxk96t","value": 19},
{"geohash": "sxk3qx","value": 21},
{"geohash": "sxk93z","value": 38},
{"geohash": "sxk97k","value": 21},
{"geohash": "sxk977","value": 32},
{"geohash": "sxk8z6","value": 31},
{"geohash": "sxk9x3","value": 99},
{"geohash": "sxkbfz","value": 57},
{"geohash": "sxk969","value": 21},
{"geohash": "sxk3bs","value": 77},
{"geohash": "sxkb72","value": 43},
{"geohash": "sxk9r9","value": 23},
{"geohash": "sxk8zh","value": 26},
{"geohash": "sxkbmb","value": 93},
{"geohash": "sxkb3x","value": 42},
{"geohash": "sxk61z","value": 99},
{"geohash": "sxkc5r","value": 99},
{"geohash": "sxkc20","value": 23},
{"geohash": "sxk1w0","value": 83},
{"geohash": "sxk92f","value": 15},
{"geohash": "sxk903","value": 32},
{"geohash": "sxk965","value": 32},
{"geohash": "sxkbgd","value": 57},
{"geohash": "sxkb6e","value": 26},
{"geohash": "sxkdhm","value": 58},
{"geohash": "sxk99k","value": 20},
{"geohash": "sxk19m","value": 77},
{"geohash": "sxk3z0","value": 40},
{"geohash": "sxkbgv","value": 60},
{"geohash": "sxk3eq","value": 45},
{"geohash": "sxkcdm","value": 108},
{"geohash": "sxk4jm","value": 85},
{"geohash": "sxkbgk","value": 44},
{"geohash": "sxk9jw","value": 23},
{"geohash": "sxkb93","value": 32},
{"geohash": "sxkbm7","value": 97},
{"geohash": "sxk91s","value": 61},
{"geohash": "sxkdkt","value": 60},
{"geohash": "sxk93w","value": 26},
{"geohash": "sxk905","value": 70},
{"geohash": "sxkbez","value": 61},
{"geohash": "sxkbdw","value": 41},
{"geohash": "sxk8yc","value": 37},
{"geohash": "sxk9tx","value": 25},
{"geohash": "sxkdhg","value": 33},
{"geohash": "sxkc0j","value": 41},
{"geohash": "sxk976","value": 25},
{"geohash": "sxk992","value": 36},
{"geohash": "sxkbe2","value": 22},
{"geohash": "sxk9g1","value": 33},
{"geohash": "sxk9p7","value": 31},
{"geohash": "sxk3f6","value": 89},
{"geohash": "sxk3bk","value": 78},
{"geohash": "sxk4jt","value": 86},
{"geohash": "sxk3sf","value": 33},
{"geohash": "sxkcej","value": 78},
{"geohash": "sxk8yu","value": 24},
{"geohash": "sxk331","value": 67},
{"geohash": "sxkdp9","value": 63},
{"geohash": "sxk3qz","value": 23},
{"geohash": "sxk9jh","value": 22},
{"geohash": "sxk33x","value": 74},
{"geohash": "sxkd5y","value": 42},
{"geohash": "sxk9s9","value": 30},
{"geohash": "sx7cv2","value": 72},
{"geohash": "sx7ckg","value": 61},
{"geohash": "sxk3z2","value": 36},
{"geohash": "sxk91y","value": 20},
{"geohash": "sxk36s","value": 55},
{"geohash": "sxkd78","value": 19},
{"geohash": "sxm445","value": 78},
{"geohash": "sxk3pn","value": 37},
{"geohash": "sxk3xs","value": 48},
{"geohash": "sxk3we","value": 55},
{"geohash": "sxk9q9","value": 31},
{"geohash": "sxk6sx","value": 77},
{"geohash": "sxk9tw","value": 28},
{"geohash": "sxkcvu","value": 79},
{"geohash": "sxk9ry","value": 18},
{"geohash": "sxk3xf","value": 29},
{"geohash": "sxkbkw","value": 75},
{"geohash": "sxk93b","value": 17},
{"geohash": "sxk3r4","value": 25},
{"geohash": "sxk19j","value": 74},
{"geohash": "sxkbe6","value": 63},
{"geohash": "sxkbk3","value": 86},
{"geohash": "sxk9b2","value": 66},
{"geohash": "sxk9b8","value": 72},
{"geohash": "sxk9dp","value": 22},
{"geohash": "sxk3sg","value": 24},
{"geohash": "sxk9u5","value": 33},
{"geohash": "sxk92x","value": 17},
{"geohash": "sxkb9j","value": 23},
{"geohash": "sxkcu9","value": 77},
{"geohash": "sxkdd6","value": 123},
{"geohash": "sxk3yb","value": 22},
{"geohash": "sxk66w","value": 92},
{"geohash": "sxkcd3","value": 85},
{"geohash": "sxk3s6","value": 26},
{"geohash": "sxkbhn","value": 64},
{"geohash": "sxk8xm","value": 59},
{"geohash": "sxk9hv","value": 33},
{"geohash": "sxkdsc","value": 50},
{"geohash": "sxk99h","value": 66},
{"geohash": "sxk3zz","value": 54},
{"geohash": "sx7fve","value": 62},
{"geohash": "sxkc40","value": 57},
{"geohash": "sxkdmz","value": 102},
{"geohash": "sxkb8m","value": 22},
{"geohash": "sx7ck8","value": 76},
{"geohash": "sxk94q","value": 70},
{"geohash": "sxk451","value": 87},
{"geohash": "sxk98r","value": 65},
{"geohash": "sxk3rx","value": 20},
{"geohash": "sxk3je","value": 16},
{"geohash": "sxkfpm","value": 85},
{"geohash": "sxk3yg","value": 32},
{"geohash": "sxkdhn","value": 42},
{"geohash": "sxk901","value": 48},
{"geohash": "sx7cz9","value": 60},
{"geohash": "sxk1t9","value": 31},
{"geohash": "sxk3nk","value": 37},
{"geohash": "sxkdpy","value": 66},
{"geohash": "sxkcuf","value": 68},
{"geohash": "sxk4pr","value": 79},
{"geohash": "sxkbgh","value": 51},
{"geohash": "sxkb8s","value": 34},
{"geohash": "sxkd5t","value": 58},
{"geohash": "sxk98z","value": 21},
{"geohash": "sxkbjf","value": 68},
{"geohash": "sxk9u2","value": 55},
{"geohash": "sxk9n1","value": 19},
{"geohash": "sxkdh2","value": 31},
{"geohash": "sxk3qt","value": 28},
{"geohash": "sxkf30","value": 99},
{"geohash": "sxkb9s","value": 26},
{"geohash": "sxk8yw","value": 32},
{"geohash": "sxkd1f","value": 86},
{"geohash": "sxkbft","value": 40},
{"geohash": "sxk97q","value": 21},
{"geohash": "sxk3s5","value": 47},
{"geohash": "sxk9jn","value": 47},
{"geohash": "sxk9kz","value": 25},
{"geohash": "sxk9qk","value": 19},
{"geohash": "sxk9dy","value": 28},
{"geohash": "sxkc1f","value": 44},
{"geohash": "sxkcfr","value": 92},
{"geohash": "sxkb9h","value": 23},
{"geohash": "sxk3z1","value": 37},
{"geohash": "sxk4ru","value": 87},
{"geohash": "sxk61w","value": 98},
{"geohash": "sxk329","value": 83},
{"geohash": "sxk99b","value": 18},
{"geohash": "sxk3xj","value": 31},
{"geohash": "sxk3rh","value": 26},
{"geohash": "sxk6q0","value": 47},
{"geohash": "sx7fr1","value": 54},
{"geohash": "sxk8yn","value": 34},
{"geohash": "sxk3pz","value": 42},
{"geohash": "sxkc56","value": 87},
{"geohash": "sxk1sf","value": 78},
{"geohash": "sxk9bu","value": 51},
{"geohash": "sxkdmy","value": 121},
{"geohash": "sxkc2g","value": 39},
{"geohash": "sxk9f1","value": 38},
{"geohash": "sxk9hr","value": 29},
{"geohash": "sxm40u","value": 80},
{"geohash": "sx7ckc","value": 73},
{"geohash": "sxk92m","value": 18},
{"geohash": "sxk6t0","value": 63},
{"geohash": "sxk97m","value": 26},
{"geohash": "sxk1rw","value": 77},
{"geohash": "sxk8yb","value": 44},
{"geohash": "sxk9rb","value": 24},
{"geohash": "sxkbgn","value": 74},
{"geohash": "sxk8yy","value": 34},
{"geohash": "sx7fpy","value": 89},
{"geohash": "sxk9gm","value": 43},
{"geohash": "sxkc1e","value": 72},
{"geohash": "sxk3xp","value": 38},
{"geohash": "sxk9d6","value": 16},
{"geohash": "sxkc98","value": 96},
{"geohash": "sxkdr7","value": 106},
{"geohash": "sxkbep","value": 30},
{"geohash": "sxk9sj","value": 27},
{"geohash": "sxk8xj","value": 59},
{"geohash": "sxkbu7","value": 110},
{"geohash": "sxk9vq","value": 39},
{"geohash": "sxkf32","value": 101},
{"geohash": "sxkb6q","value": 41},
{"geohash": "sxk97j","value": 21},
{"geohash": "sx7fky","value": 90},
{"geohash": "sxk96f","value": 18},
{"geohash": "sxkcez","value": 95},
{"geohash": "sxkb6n","value": 36},
{"geohash": "sxk9u3","value": 75},
{"geohash": "sxkcdu","value": 76},
{"geohash": "sxk9su","value": 36},
{"geohash": "sxk9eu","value": 17},
{"geohash": "sxk9rs","value": 25},
{"geohash": "sxkb9c","value": 30},
{"geohash": "sxk38t","value": 98},
{"geohash": "sxk6ss","value": 99},
{"geohash": "sxk3e2","value": 29},
{"geohash": "sxk9ne","value": 23},
{"geohash": "sxk91w","value": 19},
{"geohash": "sxk6dh","value": 58},
{"geohash": "sxk3zu","value": 80},
{"geohash": "sxk1rg","value": 79},
{"geohash": "sxkbv6","value": 45},
{"geohash": "sxk9n9","value": 28},
{"geohash": "sxk60m","value": 88},
{"geohash": "sxk985","value": 45},
{"geohash": "sxk9mp","value": 23},
{"geohash": "sxkdjj","value": 34},
{"geohash": "sxkc6b","value": 85},
{"geohash": "sxkbuv","value": 33},
{"geohash": "sxk99p","value": 56},
{"geohash": "sxk6ds","value": 30},
{"geohash": "sxk9mm","value": 23},
{"geohash": "sxkbbc","value": 72},
{"geohash": "sxk4rx","value": 65},
{"geohash": "sxk9w5","value": 35},
{"geohash": "sxk9jg","value": 17},
{"geohash": "sxk6dt","value": 68},
{"geohash": "sxk1es","value": 77},
{"geohash": "sxk6xf","value": 85},
{"geohash": "sxkc1j","value": 22},
{"geohash": "sxk9th","value": 46},
{"geohash": "sxk1sh","value": 84},
{"geohash": "sxk9nk","value": 17},
{"geohash": "sxk3k1","value": 36},
{"geohash": "sxkc0n","value": 49},
{"geohash": "sxk97n","value": 24},
{"geohash": "sxk6u3","value": 71},
{"geohash": "sxk9mx","value": 28},
{"geohash": "sx7fw3","value": 81},
{"geohash": "sxk3jg","value": 33},
{"geohash": "sxk1rz","value": 76},
{"geohash": "sxk35r","value": 22},
{"geohash": "sxkdk8","value": 28},
{"geohash": "sxk96h","value": 37},
{"geohash": "sxkdqj","value": 102},
{"geohash": "sxk8zb","value": 32},
{"geohash": "sxk6qt","value": 46},
{"geohash": "sxk3ks","value": 44},
{"geohash": "sxkbjz","value": 101},
{"geohash": "sxk9r4","value": 21},
{"geohash": "sx7cxs","value": 75},
{"geohash": "sxkb97","value": 33},
{"geohash": "sxkcfk","value": 64},
{"geohash": "sxkdsd","value": 55},
{"geohash": "sxk973","value": 12},
{"geohash": "sxk9hy","value": 41},
{"geohash": "sxk6g1","value": 75},
{"geohash": "sxkc27","value": 85},
{"geohash": "sxk6t1","value": 68},
{"geohash": "sxk6w7","value": 100},
{"geohash": "sxk3t3","value": 27},
{"geohash": "sxkcvy","value": 69},
{"geohash": "sxkcsr","value": 75},
{"geohash": "sxk38x","value": 82},
{"geohash": "sx7fr4","value": 79},
{"geohash": "sxk8yj","value": 60},
{"geohash": "sxk9m6","value": 29},
{"geohash": "sx7fmg","value": 100},
{"geohash": "sxk90v","value": 19},
{"geohash": "sxkb6w","value": 15},
{"geohash": "sxk90t","value": 30},
{"geohash": "sxk4pm","value": 49},
{"geohash": "sxk9gn","value": 36},
{"geohash": "sxkbdc","value": 71},
{"geohash": "sxk937","value": 27},
{"geohash": "sxkc24","value": 28},
{"geohash": "sxk1gg","value": 88},
{"geohash": "sxk8zp","value": 44},
{"geohash": "sxkc0r","value": 22},
{"geohash": "sxk3ex","value": 44},
{"geohash": "sxk6db","value": 71},
{"geohash": "sxkbgb","value": 37},
{"geohash": "sxkb3z","value": 37},
{"geohash": "sxk9jq","value": 27},
{"geohash": "sxk1x9","value": 93},
{"geohash": "sxkb5p","value": 51},
{"geohash": "sxkd1s","value": 72},
{"geohash": "sxkc3b","value": 42},
{"geohash": "sxk6g4","value": 80},
{"geohash": "sxkc5q","value": 91},
{"geohash": "sxk1ct","value": 96},
{"geohash": "sxkd1c","value": 74},
{"geohash": "sxk93g","value": 28},
{"geohash": "sxk9du","value": 56},
{"geohash": "sxk9qp","value": 24},
{"geohash": "sxk921","value": 15},
{"geohash": "sxkdku","value": 41},
{"geohash": "sxk3rt","value": 29},
{"geohash": "sxk1ek","value": 69},
{"geohash": "sxk92k","value": 21},
{"geohash": "sxk9e0","value": 44},
{"geohash": "sxk93r","value": 42},
{"geohash": "sxk3z5","value": 45},
{"geohash": "sxk3tg","value": 34},
{"geohash": "sxk3pw","value": 60},
{"geohash": "sxkdhv","value": 27},
{"geohash": "sxk19w","value": 77},
{"geohash": "sxk8zt","value": 32},
{"geohash": "sxk459","value": 85},
{"geohash": "sxkb7b","value": 53},
{"geohash": "sxkdpz","value": 74},
{"geohash": "sxkbfu","value": 46},
{"geohash": "sxk8xw","value": 29},
{"geohash": "sxk3pb","value": 20},
{"geohash": "sxk39j","value": 82},
{"geohash": "sxk3sb","value": 35},
{"geohash": "sxk3qr","value": 38},
{"geohash": "sxk9dj","value": 17},
{"geohash": "sxk9ph","value": 24},
{"geohash": "sxk3r3","value": 17},
{"geohash": "sxk99n","value": 44},
{"geohash": "sxk6mw","value": 48},
{"geohash": "sxk1b9","value": 85},
{"geohash": "sxk37e","value": 26},
{"geohash": "sxk925","value": 16},
{"geohash": "sxk397","value": 76},
{"geohash": "sxk4pk","value": 17},
{"geohash": "sxkc1r","value": 36},
{"geohash": "sxk938","value": 29},
{"geohash": "sxk8yp","value": 22},
{"geohash": "sx7fq5","value": 97},
{"geohash": "sxk9y5","value": 49},
{"geohash": "sxk1v1","value": 91},
{"geohash": "sxkc1p","value": 24},
{"geohash": "sxkb9k","value": 37},
{"geohash": "sxk9q1","value": 25},
{"geohash": "sxkf2c","value": 103},
{"geohash": "sxkbsq","value": 40},
{"geohash": "sxk3bb","value": 79},
{"geohash": "sxk96n","value": 44},
{"geohash": "sxk3jk","value": 17},
{"geohash": "sxkcv7","value": 73},
{"geohash": "sxkdhd","value": 30},
{"geohash": "sxk9qb","value": 19},
{"geohash": "sxkdkw","value": 31},
{"geohash": "sxk9m3","value": 41},
{"geohash": "sxkdjn","value": 18},
{"geohash": "sxk9k7","value": 19},
{"geohash": "sxk9jb","value": 29},
{"geohash": "sxk9tr","value": 35},
{"geohash": "sxk9mt","value": 17},
{"geohash": "sxk9d2","value": 20},
{"geohash": "sxkcdf","value": 80},
{"geohash": "sxk3x1","value": 23},
{"geohash": "sxk9t6","value": 24},
{"geohash": "sxk8zr","value": 22},
{"geohash": "sx7chw","value": 72},
{"geohash": "sxkd8k","value": 45},
{"geohash": "sxk9j9","value": 27},
{"geohash": "sxk9kb","value": 27},
{"geohash": "sxk8zn","value": 30},
{"geohash": "sxkbew","value": 46},
{"geohash": "sxkdpu","value": 81},
{"geohash": "sxk372","value": 17},
{"geohash": "sxk3bw","value": 104},
{"geohash": "sxk970","value": 52},
{"geohash": "sxk9ht","value": 26},
{"geohash": "sxk9jd","value": 20},
{"geohash": "sxk3x8","value": 20},
{"geohash": "sxk1tc","value": 66},
{"geohash": "sxk676","value": 47},
{"geohash": "sxk9hx","value": 25},
{"geohash": "sxk3jr","value": 35},
{"geohash": "sxk3rz","value": 19},
{"geohash": "sxkc3p","value": 116},
{"geohash": "sxk6m3","value": 37},
{"geohash": "sxkf2z","value": 43},
{"geohash": "sxk9q0","value": 35},
{"geohash": "sxkc0f","value": 49},
{"geohash": "sxk6ry","value": 81},
{"geohash": "sxk9me","value": 18},
{"geohash": "sxk6k6","value": 59},
{"geohash": "sxk38y","value": 83},
{"geohash": "sxkc0k","value": 37},
{"geohash": "sxk961","value": 43},
{"geohash": "sxk8yg","value": 22},
{"geohash": "sxk9bc","value": 16},
{"geohash": "sxkbs9","value": 80},
{"geohash": "sxk3zv","value": 84},
{"geohash": "sxkc1h","value": 34},
{"geohash": "sxk9ps","value": 26},
{"geohash": "sxk3ff","value": 87},
{"geohash": "sxk9vu","value": 39},
{"geohash": "sxkc57","value": 81},
{"geohash": "sxkc51","value": 77},
{"geohash": "sxkc60","value": 53},
{"geohash": "sxkbfc","value": 44},
{"geohash": "sxkbgg","value": 57},
{"geohash": "sxk90s","value": 31},
{"geohash": "sx7fw9","value": 74},
{"geohash": "sxk63b","value": 99},
{"geohash": "sxk3m1","value": 22},
{"geohash": "sxkc4r","value": 101},
{"geohash": "sxk9g0","value": 27},
{"geohash": "sx7cuc","value": 81},
{"geohash": "sx7fpp","value": 59},
{"geohash": "sxkcfv","value": 75},
{"geohash": "sxk93n","value": 17},
{"geohash": "sxk8wz","value": 34},
{"geohash": "sxkd40","value": 67},
{"geohash": "sxk96c","value": 21},
{"geohash": "sxkc0y","value": 23},
{"geohash": "sxk9d5","value": 32},
{"geohash": "sxkd85","value": 111},
{"geohash": "sxk1fw","value": 91},
{"geohash": "sxkbve","value": 116},
{"geohash": "sxk9hs","value": 19},
{"geohash": "sxk99s","value": 17},
{"geohash": "sxkbkt","value": 77},
{"geohash": "sxkf27","value": 76},
{"geohash": "sxk9v4","value": 18},
{"geohash": "sxk3n4","value": 30},
{"geohash": "sxk960","value": 28},
{"geohash": "sxk1fj","value": 84},
{"geohash": "sxkb98","value": 45},
{"geohash": "sxk9v0","value": 75},
{"geohash": "sxk9kc","value": 20},
{"geohash": "sxk6de","value": 36},
{"geohash": "sxk1cv","value": 91},
{"geohash": "sxk9nv","value": 26},
{"geohash": "sx7fr8","value": 85},
{"geohash": "sxkbsh","value": 22},
{"geohash": "sxk92w","value": 19},
{"geohash": "sxkcu0","value": 79},
{"geohash": "sxkdqm","value": 106},
{"geohash": "sxk8yd","value": 57},
{"geohash": "sxkb7n","value": 59},
{"geohash": "sxkc03","value": 58},
{"geohash": "sxkbj4","value": 71},
{"geohash": "sxkdkk","value": 44},
{"geohash": "sxk96e","value": 22},
{"geohash": "sxkb7r","value": 38},
{"geohash": "sxk9q2","value": 38},
{"geohash": "sxk99f","value": 18},
{"geohash": "sxk8zm","value": 32},
{"geohash": "sxk3g8","value": 37},
{"geohash": "sxkbk6","value": 89},
{"geohash": "sxk9pb","value": 71},
{"geohash": "sxk377","value": 26},
{"geohash": "sxk6ps","value": 98},
{"geohash": "sxk9c2","value": 36},
{"geohash": "sxk9e7","value": 27},
{"geohash": "sxkc04","value": 32},
{"geohash": "sxk9tg","value": 34},
{"geohash": "sxkd50","value": 40},
{"geohash": "sx7cxm","value": 80},
{"geohash": "sxk6we","value": 103},
{"geohash": "sxk9w6","value": 38},
{"geohash": "sxk3t6","value": 25},
{"geohash": "sxkdpf","value": 71},
{"geohash": "sxk6dz","value": 75},
{"geohash": "sxk9c0","value": 19},
{"geohash": "sxkcd2","value": 78},
{"geohash": "sxkd44","value": 29},
{"geohash": "sxk9pw","value": 37},
{"geohash": "sxkc0u","value": 49},
{"geohash": "sxk9zr","value": 56},
{"geohash": "sxk9g8","value": 30},
{"geohash": "sxk9c8","value": 48},
{"geohash": "sxkc63","value": 79},
{"geohash": "sxk3rp","value": 27},
{"geohash": "sxkcfu","value": 61},
{"geohash": "sxk3su","value": 34},
{"geohash": "sx7fvk","value": 64},
{"geohash": "sxk9qx","value": 44},
{"geohash": "sxk6k7","value": 39},
{"geohash": "sxk3zt","value": 99},
{"geohash": "sxkbuy","value": 55},
{"geohash": "sxk6nr","value": 43},
{"geohash": "sxk3jm","value": 26},
{"geohash": "sxkfn3","value": 71},
{"geohash": "sxk6u1","value": 82},
{"geohash": "sxk1xd","value": 92},
{"geohash": "sxk3xk","value": 34},
{"geohash": "sxkdhk","value": 23},
{"geohash": "sxkdsu","value": 35},
{"geohash": "sxk9m7","value": 19},
{"geohash": "sxk407","value": 96},
{"geohash": "sxk9c7","value": 32},
{"geohash": "sxk6dd","value": 25},
{"geohash": "sxkc2r","value": 59},
{"geohash": "sxk9y4","value": 27},
{"geohash": "sxk9yv","value": 44},
{"geohash": "sxk3jw","value": 32},
{"geohash": "sxk1w5","value": 99},
{"geohash": "sxk1tx","value": 101},
{"geohash": "sxkbg0","value": 50},
{"geohash": "sxk987","value": 56},
{"geohash": "sx7cwv","value": 76},
{"geohash": "sxk3r2","value": 15},
{"geohash": "sxk9ey","value": 15},
{"geohash": "sxk9p1","value": 38},
{"geohash": "sxk9ny","value": 20},
{"geohash": "sxkb79","value": 34},
{"geohash": "sxk9j2","value": 60},
{"geohash": "sxk9mj","value": 21},
{"geohash": "sxk967","value": 31},
{"geohash": "sxk9w8","value": 44},
{"geohash": "sxk6nt","value": 52},
{"geohash": "sxk3s7","value": 23},
{"geohash": "sxkb9t","value": 22},
{"geohash": "sxkb8x","value": 48},
{"geohash": "sxkcdr","value": 105},
{"geohash": "sxkdkm","value": 39},
{"geohash": "sxkbeq","value": 65},
{"geohash": "sxm417","value": 41},
{"geohash": "sxkbbs","value": 52},
{"geohash": "sxm40n","value": 69},
{"geohash": "sxk9sr","value": 40},
{"geohash": "sxk920","value": 12},
{"geohash": "sxk33u","value": 53},
{"geohash": "sxkc5t","value": 72},
{"geohash": "sxk9q3","value": 19},
{"geohash": "sxk44c","value": 96},
{"geohash": "sxk9ut","value": 43},
{"geohash": "sxk6sg","value": 71},
{"geohash": "sxk94p","value": 20},
{"geohash": "sxkdeb","value": 98},
{"geohash": "sxk3rk","value": 15},
{"geohash": "sxk9y1","value": 20},
{"geohash": "sxk4jh","value": 89},
{"geohash": "sxk9c6","value": 26},
{"geohash": "sxk657","value": 42},
{"geohash": "sxk3x2","value": 19},
{"geohash": "sxk98d","value": 18},
{"geohash": "sxk3z7","value": 42},
{"geohash": "sxk9wm","value": 43},
{"geohash": "sxk9jx","value": 19},
{"geohash": "sxk9ef","value": 20},
{"geohash": "sxk665","value": 89},
{"geohash": "sxkbd2","value": 72},
{"geohash": "sxk6wg","value": 103},
{"geohash": "sxk933","value": 21},
{"geohash": "sxk3jf","value": 25},
{"geohash": "sxkb84","value": 51},
{"geohash": "sxkbb8","value": 19},
{"geohash": "sxk9v3","value": 35},
{"geohash": "sxkc3u","value": 68},
{"geohash": "sxk442","value": 93},
{"geohash": "sxk96d","value": 25},
{"geohash": "sxk9pm","value": 20},
{"geohash": "sxk6sw","value": 70},
{"geohash": "sxk931","value": 18},
{"geohash": "sxk6e1","value": 96},
{"geohash": "sxk9b6","value": 70},
{"geohash": "sxk33f","value": 42},
{"geohash": "sxkd8d","value": 93},
{"geohash": "sxkd2k","value": 41},
{"geohash": "sx7cxv","value": 77},
{"geohash": "sxk9vc","value": 17},
{"geohash": "sxk1g7","value": 95},
{"geohash": "sxk6wh","value": 85},
{"geohash": "sxkbm6","value": 91},
{"geohash": "sxk6pt","value": 99},
{"geohash": "sxkcex","value": 64},
{"geohash": "sxk9wb","value": 32},
{"geohash": "sxk9nj","value": 23},
{"geohash": "sxk9r1","value": 20},
{"geohash": "sxkd7z","value": 87},
{"geohash": "sxk93p","value": 12},
{"geohash": "sxk96u","value": 25},
{"geohash": "sxk9mn","value": 21},
{"geohash": "sxk9t5","value": 32},
{"geohash": "sxk45d","value": 95},
{"geohash": "sxk9ke","value": 21},
{"geohash": "sxk3s1","value": 63},
{"geohash": "sxk98y","value": 34},
{"geohash": "sxk9x9","value": 101},
{"geohash": "sxk9u7","value": 31},
{"geohash": "sxk6q4","value": 26},
{"geohash": "sxkbg3","value": 78},
{"geohash": "sxkbgj","value": 55},
{"geohash": "sxk97w","value": 22},
{"geohash": "sxk6mc","value": 28},
{"geohash": "sxk3m2","value": 29},
{"geohash": "sxkb75","value": 43},
{"geohash": "sx7ghc","value": 55},
{"geohash": "sxk9bt","value": 69},
{"geohash": "sxk9p0","value": 48},
{"geohash": "sxk99g","value": 16},
{"geohash": "sxk93v","value": 20},
{"geohash": "sxk9uu","value": 37},
{"geohash": "sxk9k6","value": 20},
{"geohash": "sxkbfb","value": 24},
{"geohash": "sxk9nu","value": 27},
{"geohash": "sxk6x4","value": 96},
{"geohash": "sxk9s0","value": 34},
{"geohash": "sxkd83","value": 91},
{"geohash": "sxk9hq","value": 28},
{"geohash": "sxk3g1","value": 85},
{"geohash": "sxk6xb","value": 38},
{"geohash": "sxk680","value": 90},
{"geohash": "sxk19y","value": 65},
{"geohash": "sxk3kd","value": 64},
{"geohash": "sxkcen","value": 72},
{"geohash": "sxk9gf","value": 45},
{"geohash": "sxkde1","value": 103},
{"geohash": "sxk92v","value": 16},
{"geohash": "sxk9ev","value": 15},
{"geohash": "sxkc42","value": 55},
{"geohash": "sxkdt0","value": 112},
{"geohash": "sxk9db","value": 17},
{"geohash": "sxk962","value": 42},
{"geohash": "sxk3qw","value": 32},
{"geohash": "sxk9bg","value": 20},
{"geohash": "sxk93u","value": 17},
{"geohash": "sxm41e","value": 82},
{"geohash": "sxkfpr","value": 66},
{"geohash": "sxkd7b","value": 24},
{"geohash": "sxkdt1","value": 100},
{"geohash": "sxk9v1","value": 30},
{"geohash": "sxk8zd","value": 24},
{"geohash": "sxkbex","value": 44},
{"geohash": "sxk458","value": 53},
{"geohash": "sxkf42","value": 98},
{"geohash": "sxk9bf","value": 27},
{"geohash": "sxk3tm","value": 34},
{"geohash": "sxk68c","value": 71},
{"geohash": "sxk3ru","value": 20},
{"geohash": "sxk9e9","value": 19},
{"geohash": "sxkbm9","value": 92},
{"geohash": "sxk1fq","value": 89},
{"geohash": "sxk4nz","value": 98},
{"geohash": "sxk3zs","value": 96},
{"geohash": "sxk9tk","value": 25},
{"geohash": "sxkd1d","value": 74},
{"geohash": "sxkbb9","value": 41},
{"geohash": "sxk1bu","value": 57},
{"geohash": "sxk67f","value": 78},
{"geohash": "sx7fmj","value": 87},
{"geohash": "sx7ctr","value": 73},
{"geohash": "sxk9mq","value": 22},
{"geohash": "sxkc4x","value": 107},
{"geohash": "sx7fvp","value": 60},
{"geohash": "sxk9pe","value": 38},
{"geohash": "sxk60n","value": 76},
{"geohash": "sxk9ff","value": 40},
{"geohash": "sxk3bm","value": 67},
{"geohash": "sxk6ws","value": 89},
{"geohash": "sxk33t","value": 70},
{"geohash": "sxk324","value": 76},
{"geohash": "sxk9fc","value": 28},
{"geohash": "sxk38s","value": 96},
{"geohash": "sx7fw8","value": 74},
{"geohash": "sxk6x1","value": 56},
{"geohash": "sxk3ne","value": 32},
{"geohash": "sxkb9g","value": 23},
{"geohash": "sxk9jr","value": 29},
{"geohash": "sxk3qg","value": 40},
{"geohash": "sxkb91","value": 29},
{"geohash": "sxk9k9","value": 21},
{"geohash": "sxk978","value": 49},
{"geohash": "sxk3z9","value": 94},
{"geohash": "sxk4ny","value": 87},
{"geohash": "sxk8zw","value": 30},
{"geohash": "sxk4r3","value": 40},
{"geohash": "sxkbgs","value": 65},
{"geohash": "sxk9n7","value": 19},
{"geohash": "sxk1t4","value": 73},
{"geohash": "sxk8z7","value": 19},
{"geohash": "sxk96v","value": 27},
{"geohash": "sxk3gd","value": 35},
{"geohash": "sxk9p6","value": 26},
{"geohash": "sxk3w4","value": 35},
{"geohash": "sxk9my","value": 23},
{"geohash": "sxk9nn","value": 23},
{"geohash": "sxk9nr","value": 44},
{"geohash": "sxkd2t","value": 89},
{"geohash": "sxk1fv","value": 92},
{"geohash": "sxk9sp","value": 24},
{"geohash": "sxk40j","value": 92},
{"geohash": "sxk6qy","value": 36},
{"geohash": "sxk9gd","value": 47},
{"geohash": "sxkcf9","value": 95},
{"geohash": "sxk3pk","value": 52},
{"geohash": "sxkbd8","value": 54},
{"geohash": "sxk3j7","value": 20},
{"geohash": "sxk3ht","value": 57},
{"geohash": "sxk92d","value": 14},
{"geohash": "sxk387","value": 103},
{"geohash": "sxk60t","value": 91},
{"geohash": "sxk9k1","value": 31},
{"geohash": "sxk3zr","value": 95},
{"geohash": "sx7cmx","value": 93},
{"geohash": "sxk6e7","value": 93},
{"geohash": "sxkcue","value": 69},
{"geohash": "sxk454","value": 86},
{"geohash": "sxk9uq","value": 43},
{"geohash": "sxk3qq","value": 36},
{"geohash": "sxk9sz","value": 21},
{"geohash": "sxk693","value": 81},
{"geohash": "sxk9ng","value": 18},
{"geohash": "sxm41g","value": 85},
{"geohash": "sxk4jw","value": 88},
{"geohash": "sxk9jm","value": 22},
{"geohash": "sxk661","value": 97},
{"geohash": "sxk8yk","value": 69},
{"geohash": "sxk4rs","value": 93},
{"geohash": "sxkbbz","value": 40},
{"geohash": "sxk6tk","value": 79},
{"geohash": "sxkbfx","value": 53},
{"geohash": "sxk9mr","value": 23},
{"geohash": "sx7fwn","value": 74},
{"geohash": "sxk997","value": 42},
{"geohash": "sxk9qr","value": 24},
{"geohash": "sxkf45","value": 93},
{"geohash": "sxk3sp","value": 50},
{"geohash": "sxkf1w","value": 99},
{"geohash": "sxk3py","value": 44},
{"geohash": "sxk98b","value": 18},
{"geohash": "sxk92y","value": 15},
{"geohash": "sxk9re","value": 18},
{"geohash": "sxk4pp","value": 101},
{"geohash": "sxkc5n","value": 105},
{"geohash": "sxk1bx","value": 98},
{"geohash": "sxkb9d","value": 37},
{"geohash": "sxkb6m","value": 32},
{"geohash": "sxk93j","value": 17},
{"geohash": "sx7cwy","value": 92},
{"geohash": "sxk1dw","value": 48},
{"geohash": "sx7ctz","value": 82},
{"geohash": "sxk92j","value": 18},
{"geohash": "sxk8xv","value": 28},
{"geohash": "sxk3r9","value": 27},
{"geohash": "sxkd48","value": 72},
{"geohash": "sxk336","value": 51},
{"geohash": "sx7ghf","value": 57},
{"geohash": "sxk9cc","value": 47},
{"geohash": "sxkbk0","value": 81},
{"geohash": "sxk1dz","value": 33},
{"geohash": "sx7cw2","value": 86},
{"geohash": "sxk9n3","value": 22},
{"geohash": "sxk90u","value": 23},
{"geohash": "sxkcu2","value": 77},
{"geohash": "sxk9ks","value": 22},
{"geohash": "sxk3pv","value": 60},
{"geohash": "sxk3rq","value": 22},
{"geohash": "sxk6pw","value": 99},
{"geohash": "sxkc3h","value": 57},
{"geohash": "sxk9hz","value": 23},
{"geohash": "sxk9dg","value": 39},
{"geohash": "sxk3rv","value": 20},
{"geohash": "sxk1s7","value": 78},
{"geohash": "sxk3yf","value": 19},
{"geohash": "sxk4nq","value": 94},
{"geohash": "sxk9c9","value": 25},
{"geohash": "sxk91q","value": 29},
{"geohash": "sxkbm3","value": 86},
{"geohash": "sxk92b","value": 24},
{"geohash": "sxk3w2","value": 52},
{"geohash": "sxk9br","value": 35},
{"geohash": "sxk3zx","value": 94},
{"geohash": "sxkddf","value": 99},
{"geohash": "sxk1wd","value": 88},
{"geohash": "sxk6xd","value": 86},
{"geohash": "sxkbvn","value": 61},
{"geohash": "sxkbeg","value": 48},
{"geohash": "sxkfjb","value": 82},
{"geohash": "sxkb8t","value": 32},
{"geohash": "sxk9r8","value": 26},
{"geohash": "sxk6mt","value": 46},
{"geohash": "sxk9um","value": 39},
{"geohash": "sx7frb","value": 88},
{"geohash": "sxk902","value": 29},
{"geohash": "sxkc68","value": 89},
{"geohash": "sxk984","value": 22},
{"geohash": "sxkc2e","value": 41},
{"geohash": "sxk6t2","value": 66},
{"geohash": "sx7czw","value": 64},
{"geohash": "sxk9rh","value": 28},
{"geohash": "sxk3qe","value": 23},
{"geohash": "sxkcv6","value": 66},
{"geohash": "sxk3zd","value": 84},
{"geohash": "sxkf24","value": 102},
{"geohash": "sxk3x3","value": 16},
{"geohash": "sxk9dk","value": 27},
{"geohash": "sxkc08","value": 36},
{"geohash": "sxk6rc","value": 98},
{"geohash": "sx7cqp","value": 72},
{"geohash": "sxk9s5","value": 22},
{"geohash": "sxk90q","value": 34},
{"geohash": "sxk37m","value": 28},
{"geohash": "sxkbsm","value": 72},
{"geohash": "sxkd2q","value": 82},
{"geohash": "sxk934","value": 21},
{"geohash": "sxk3ce","value": 95},
{"geohash": "sxk9fb","value": 20},
{"geohash": "sxk4h1","value": 84},
{"geohash": "sxk3pr","value": 52},
{"geohash": "sxk935","value": 19},
{"geohash": "sxk8yz","value": 17},
{"geohash": "sxk3xg","value": 50},
{"geohash": "sxkbv5","value": 114},
{"geohash": "sxkbsk","value": 89},
{"geohash": "sxk6th","value": 87},
{"geohash": "sxkbvj","value": 66},
{"geohash": "sxkf25","value": 105},
{"geohash": "sxk3tq","value": 35},
{"geohash": "sxk1wh","value": 91},
{"geohash": "sxk3z8","value": 86},
{"geohash": "sxk9bn","value": 68},
{"geohash": "sxkcdv","value": 76},
{"geohash": "sxkcf3","value": 94},
{"geohash": "sxk9d9","value": 29},
{"geohash": "sxk9ce","value": 22},
{"geohash": "sxk3xc","value": 31},
{"geohash": "sxk9tv","value": 52},
{"geohash": "sxk9t7","value": 24},
{"geohash": "sxk9mg","value": 17},
{"geohash": "sxkc6r","value": 63},
{"geohash": "sxk9vh","value": 25},
{"geohash": "sxk9wh","value": 31},
{"geohash": "sxk6k4","value": 71},
{"geohash": "sxk6r8","value": 98},
{"geohash": "sxk906","value": 58},
{"geohash": "sxkb7j","value": 73},
{"geohash": "sxk9hu","value": 29},
{"geohash": "sxk8yq","value": 20},
{"geohash": "sxkfph","value": 80},
{"geohash": "sxk93k","value": 28},
{"geohash": "sxk9v7","value": 30},
{"geohash": "sxk98j","value": 67},
{"geohash": "sxk989","value": 28},
{"geohash": "sxkc21","value": 19},
{"geohash": "sx7fr6","value": 82},
{"geohash": "sxk3gb","value": 44},
{"geohash": "sxkbkm","value": 81},
{"geohash": "sxk6x7","value": 93},
{"geohash": "sxk1wc","value": 96},
{"geohash": "sxkd5x","value": 28},
{"geohash": "sxk6xj","value": 87},
{"geohash": "sxk9dt","value": 22},
{"geohash": "sxk3w8","value": 29},
{"geohash": "sxkbuz","value": 17},
{"geohash": "sxkf2f","value": 111},
{"geohash": "sxk4pv","value": 41},
{"geohash": "sxk995","value": 67},
{"geohash": "sxk9nm","value": 30},
{"geohash": "sxkb73","value": 35},
{"geohash": "sxk3hv","value": 60},
{"geohash": "sxk91u","value": 65},
{"geohash": "sxkc2m","value": 83},
{"geohash": "sxkbby","value": 47},
{"geohash": "sxk4nw","value": 75},
{"geohash": "sxk3qs","value": 27},
{"geohash": "sx7fkq","value": 96},
{"geohash": "sxk9em","value": 17},
{"geohash": "sxkbkk","value": 89},
{"geohash": "sxk664","value": 97},
{"geohash": "sxkbe9","value": 43},
{"geohash": "sxkd1y","value": 41},
{"geohash": "sxk4rk","value": 34},
{"geohash": "sxk1x1","value": 99},
{"geohash": "sxk4pu","value": 75},
{"geohash": "sxk365","value": 60},
{"geohash": "sxkcgt","value": 82},
{"geohash": "sxk8yf","value": 23},
{"geohash": "sxk3jq","value": 36},
{"geohash": "sxk3r7","value": 21},
{"geohash": "sxk9yy","value": 44},
{"geohash": "sxk94x","value": 40},
{"geohash": "sxk1ud","value": 95},
{"geohash": "sxk9n6","value": 20},
{"geohash": "sxk9vw","value": 31},
{"geohash": "sxk3p7","value": 38},
{"geohash": "sxkd45","value": 33},
{"geohash": "sxk92q","value": 22},
{"geohash": "sx7cxk","value": 84},
{"geohash": "sxk9c3","value": 23},
{"geohash": "sxk96x","value": 31},
{"geohash": "sxkbdq","value": 26},
{"geohash": "sxkc53","value": 71},
{"geohash": "sxkd32","value": 18},
{"geohash": "sxkd00","value": 19},
{"geohash": "sxk9yt","value": 48},
{"geohash": "sxk1u5","value": 86},
{"geohash": "sxk6px","value": 94},
{"geohash": "sxk4rt","value": 94},
{"geohash": "sx7ckf","value": 79},
{"geohash": "sxk92c","value": 17},
{"geohash": "sxk1cj","value": 99},
{"geohash": "sxk9t1","value": 20},
{"geohash": "sxkb8k","value": 25},
{"geohash": "sxkd81","value": 89},
{"geohash": "sxk9qs","value": 21},
{"geohash": "sxkcdd","value": 86},
{"geohash": "sxk6wb","value": 58},
{"geohash": "sxk9ft","value": 67},
{"geohash": "sxkbdx","value": 29},
{"geohash": "sx7cze","value": 65},
{"geohash": "sxk1em","value": 67},
{"geohash": "sxk37d","value": 31},
{"geohash": "sxk656","value": 59},
{"geohash": "sxk932","value": 33},
{"geohash": "sxk8xn","value": 60},
{"geohash": "sx7fqg","value": 85},
{"geohash": "sxkc5p","value": 98},
{"geohash": "sxk9rd","value": 20},
{"geohash": "sx7cxj","value": 64},
{"geohash": "sxk9fx","value": 63},
{"geohash": "sxk3bq","value": 80},
{"geohash": "sxk1cz","value": 47},
{"geohash": "sxk96k","value": 28},
{"geohash": "sxkd46","value": 37},
{"geohash": "sxk9u0","value": 23},
{"geohash": "sxkf26","value": 103},
{"geohash": "sxk97t","value": 23},
{"geohash": "sxk8z1","value": 24},
{"geohash": "sxk689","value": 76},
{"geohash": "sxk1tt","value": 92},
{"geohash": "sxk97h","value": 35},
{"geohash": "sxk3tc","value": 42},
{"geohash": "sxk1fb","value": 42},
{"geohash": "sx7fmm","value": 87},
{"geohash": "sxk8xg","value": 49},
{"geohash": "sxk61q","value": 93},
{"geohash": "sxk3jv","value": 19},
{"geohash": "sxkb96","value": 38},
{"geohash": "sxkb8f","value": 45},
{"geohash": "sxk60q","value": 85},
{"geohash": "sxk986","value": 32},
{"geohash": "sxk91m","value": 33},
{"geohash": "sxk3bc","value": 84},
{"geohash": "sxk9r3","value": 20},
{"geohash": "sxk6q5","value": 32},
{"geohash": "sxk9qc","value": 21},
{"geohash": "sxkc48","value": 40},
{"geohash": "sxk6dw","value": 78},
{"geohash": "sxkbef","value": 36},
{"geohash": "sx7fqx","value": 79},
{"geohash": "sxk9bp","value": 46},
{"geohash": "sxk971","value": 19},
{"geohash": "sxk9hf","value": 20},
{"geohash": "sxk3w1","value": 48},
{"geohash": "sxkd84","value": 108},
{"geohash": "sxkc1n","value": 25},
{"geohash": "sxkbg1","value": 50},
{"geohash": "sxk1bz","value": 99},
{"geohash": "sxk9gh","value": 48},
{"geohash": "sxkc5k","value": 89},
{"geohash": "sxk3k9","value": 54},
{"geohash": "sxk927","value": 23},
{"geohash": "sxk97z","value": 21},
{"geohash": "sxk3wc","value": 30},
{"geohash": "sxk3k3","value": 28},
{"geohash": "sxk8zk","value": 17},
{"geohash": "sxkbj1","value": 65},
{"geohash": "sxkbvr","value": 92},
{"geohash": "sxk3k2","value": 26},
{"geohash": "sxkd43","value": 41},
{"geohash": "sxk9g2","value": 31},
{"geohash": "sxk9kr","value": 34},
{"geohash": "sxkbut","value": 71},
{"geohash": "sxk8xr","value": 27},
{"geohash": "sxkbbd","value": 48},
{"geohash": "sxkbuk","value": 90},
{"geohash": "sxk97s","value": 33},
{"geohash": "sxk3nu","value": 33},
{"geohash": "sxk3t4","value": 23},
{"geohash": "sxk9sx","value": 22},
{"geohash": "sxk9jv","value": 19},
{"geohash": "sxk6sy","value": 69},
{"geohash": "sxk63c","value": 87},
{"geohash": "sxkdhb","value": 29},
{"geohash": "sx7ghq","value": 67},
{"geohash": "sxk900","value": 25},
{"geohash": "sxk9gp","value": 37},
{"geohash": "sxkc5s","value": 77},
{"geohash": "sxk325","value": 81},
{"geohash": "sxkd5w","value": 26},
{"geohash": "sxkdhf","value": 39},
{"geohash": "sx7fpt","value": 48},
{"geohash": "sxk9rt","value": 45},
{"geohash": "sxk8ze","value": 25},
{"geohash": "sxkc0b","value": 42},
{"geohash": "sxk982","value": 16},
{"geohash": "sxk9m2","value": 29},
{"geohash": "sxk966","value": 23},
{"geohash": "sxkd89","value": 89},
{"geohash": "sx7cww","value": 90},
{"geohash": "sxk3pc","value": 50},
{"geohash": "sxk91j","value": 19},
{"geohash": "sxkbge","value": 43},
{"geohash": "sxk3kv","value": 46},
{"geohash": "sxkd1e","value": 71},
{"geohash": "sx7ghe","value": 20},
{"geohash": "sxk9qg","value": 21},
{"geohash": "sxk9qq","value": 22},
{"geohash": "sxkdp2","value": 75},
{"geohash": "sxkd1k","value": 71},
{"geohash": "sxk3ev","value": 88},
{"geohash": "sxkcuc","value": 78},
{"geohash": "sxk9er","value": 24},
{"geohash": "sxkb6g","value": 60},
{"geohash": "sxk9t0","value": 17},
{"geohash": "sxk9r2","value": 21},
{"geohash": "sxk6w5","value": 103},
{"geohash": "sxkf1r","value": 105},
{"geohash": "sxkdrk","value": 74},
{"geohash": "sxk3yc","value": 33},
{"geohash": "sxkc29","value": 22},
{"geohash": "sxk6m1","value": 40},
{"geohash": "sxk3xb","value": 26},
{"geohash": "sxk3qu","value": 26},
{"geohash": "sxk3pj","value": 35},
{"geohash": "sxkdh6","value": 34},
{"geohash": "sxk4pt","value": 71},
{"geohash": "sxk99v","value": 26},
{"geohash": "sxkb6j","value": 46},
{"geohash": "sxkd1u","value": 36},
{"geohash": "sxkbbb","value": 68},
{"geohash": "sxk9vk","value": 28},
{"geohash": "sxk9dm","value": 21},
{"geohash": "sxk9kt","value": 21},
{"geohash": "sxkb78","value": 45},
{"geohash": "sxk9kg","value": 19},
{"geohash": "sxkc2q","value": 86},
{"geohash": "sxk9vm","value": 30},
{"geohash": "sxk91r","value": 24},
{"geohash": "sxm41s","value": 70},
{"geohash": "sxk6rg","value": 73},
{"geohash": "sxkbhs","value": 80},
{"geohash": "sxk99z","value": 25},
{"geohash": "sxk3fd","value": 94},
{"geohash": "sxk988","value": 17},
{"geohash": "sxk6k9","value": 41},
{"geohash": "sxk996","value": 42},
{"geohash": "sxkf2y","value": 58},
{"geohash": "sxk66z","value": 70},
{"geohash": "sxk6dc","value": 62},
{"geohash": "sxkd41","value": 70},
{"geohash": "sxk9b7","value": 48},
{"geohash": "sxk93q","value": 32},
{"geohash": "sxkdsg","value": 55},
{"geohash": "sx7fw5","value": 84},
{"geohash": "sx7cxu","value": 76},
{"geohash": "sxk9st","value": 23},
{"geohash": "sxk9wd","value": 38},
{"geohash": "sxk1dn","value": 66},
{"geohash": "sxk6x3","value": 56},
{"geohash": "sxk3b8","value": 65},
{"geohash": "sxkc39","value": 33},
{"geohash": "sxkcv1","value": 54},
{"geohash": "sx7cxw","value": 67},
{"geohash": "sxkde3","value": 100},
{"geohash": "sxkc6n","value": 58},
{"geohash": "sxkcdq","value": 100},
{"geohash": "sxkbbt","value": 35},
{"geohash": "sxk98t","value": 62},
{"geohash": "sxk18j","value": 76},
{"geohash": "sxk3xw","value": 65},
{"geohash": "sxk3jp","value": 42},
{"geohash": "sx7cxe","value": 68},
{"geohash": "sxk939","value": 35},
{"geohash": "sxk98s","value": 52},
{"geohash": "sxk904","value": 57},
{"geohash": "sxk9df","value": 33},
{"geohash": "sxk8z4","value": 22},
{"geohash": "sxk3sk","value": 26},
{"geohash": "sxk99c","value": 17},
{"geohash": "sxk3rr","value": 25},
{"geohash": "sxk9pv","value": 24},
{"geohash": "sxk90p","value": 13},
{"geohash": "sxk9k5","value": 31},
{"geohash": "sxkbe1","value": 52},
{"geohash": "sxk91x","value": 21},
{"geohash": "sxk9zn","value": 42},
{"geohash": "sxk9tf","value": 39},
{"geohash": "sxkcd4","value": 103},
{"geohash": "sxk9qf","value": 21},
{"geohash": "sxk6nu","value": 51},
{"geohash": "sxk96j","value": 40},
{"geohash": "sxk915","value": 56},
{"geohash": "sxkc0h","value": 34},
{"geohash": "sx7cwn","value": 88},
{"geohash": "sxk6m9","value": 54},
{"geohash": "sxk384","value": 103},
{"geohash": "sxkcuq","value": 74},
{"geohash": "sxk90j","value": 42},
{"geohash": "sxk9nz","value": 30},
{"geohash": "sxk9gj","value": 40},
{"geohash": "sxk3kb","value": 45},
{"geohash": "sxk4xb","value": 92},
{"geohash": "sxk3c4","value": 87},
{"geohash": "sxk3gm","value": 30},
{"geohash": "sxk9sy","value": 24},
{"geohash": "sxk9fs","value": 66},
{"geohash": "sxk4pb","value": 33},
{"geohash": "sxkcuw","value": 74},
{"geohash": "sxhzvq","value": 76},
{"geohash": "sxk9d7","value": 19},
{"geohash": "sxk1b2","value": 81},
{"geohash": "sxk3r5","value": 20},
{"geohash": "sxk9rm","value": 21},
{"geohash": "sxkcvv","value": 69},
{"geohash": "sxk9w2","value": 26},
{"geohash": "sxkd2m","value": 86},
{"geohash": "sxk3x7","value": 32},
{"geohash": "sxk6nw","value": 65},
{"geohash": "sxk9ys","value": 73},
{"geohash": "sxk9y0","value": 21},
{"geohash": "sx7czs","value": 53},
{"geohash": "sx7cv0","value": 50},
{"geohash": "sxkc54","value": 92},
{"geohash": "sxk92n","value": 16},
{"geohash": "sx7chk","value": 80},
{"geohash": "sxkdqs","value": 100},
{"geohash": "sxk3jj","value": 23},
{"geohash": "sxk393","value": 80},
{"geohash": "sxk602","value": 92},
{"geohash": "sxk1by","value": 97},
{"geohash": "sxk1te","value": 54},
{"geohash": "sxkdsf","value": 36},
{"geohash": "sxkbgm","value": 56},
{"geohash": "sxk9bv","value": 99},
{"geohash": "sxk6fb","value": 74},
{"geohash": "sxk90r","value": 15},
{"geohash": "sxk3kg","value": 35},
{"geohash": "sxk9tb","value": 29},
{"geohash": "sxkdqe","value": 94},
{"geohash": "sxkf2u","value": 57},
{"geohash": "sxkbj3","value": 59},
{"geohash": "sxk6qz","value": 72},
{"geohash": "sxk983","value": 20},
{"geohash": "sxkbs6","value": 80},
{"geohash": "sxk9pp","value": 34},
{"geohash": "sxkd1q","value": 82},
{"geohash": "sxkf31","value": 103},
{"geohash": "sxkc3g","value": 77},
{"geohash": "sxkbd9","value": 74},
{"geohash": "sxkd1x","value": 34},
{"geohash": "sxkd1m","value": 80},
{"geohash": "sxk6ms","value": 35},
{"geohash": "sxk90y","value": 37},
{"geohash": "sxkdkc","value": 27},
{"geohash": "sxk9bk","value": 51},
{"geohash": "sxk6p5","value": 38},
{"geohash": "sxkbkz","value": 73},
{"geohash": "sxk3qp","value": 47},
{"geohash": "sxkdse","value": 71},
{"geohash": "sxk9bd","value": 42},
{"geohash": "sxk91z","value": 15},
{"geohash": "sxkb6s","value": 37},
{"geohash": "sxk3er","value": 20},
{"geohash": "sxk3wf","value": 23},
{"geohash": "sxkcsp","value": 90},
{"geohash": "sxk8zx","value": 57},
{"geohash": "sxk6ee","value": 99},
{"geohash": "sxk66u","value": 64},
{"geohash": "sxk1ru","value": 83},
{"geohash": "sxk9k8","value": 25},
{"geohash": "sxkbfy","value": 58},
{"geohash": "sxkcv4","value": 73},
{"geohash": "sxk6pe","value": 92},
{"geohash": "sxk9rv","value": 33},
{"geohash": "sxk96q","value": 29},
{"geohash": "sxk3g9","value": 31},
{"geohash": "sxkfn2","value": 77},
{"geohash": "sxk3th","value": 30},
{"geohash": "sxkbuj","value": 73},
{"geohash": "sx7fvm","value": 69},
{"geohash": "sxk6mr","value": 55},
{"geohash": "sx7gj0","value": 59},
{"geohash": "sx7fr5","value": 92},
{"geohash": "sxk601","value": 93},
{"geohash": "sxk9k0","value": 55},
{"geohash": "sxk376","value": 29},
{"geohash": "sxkcve","value": 71},
{"geohash": "sxk9qe","value": 22},
{"geohash": "sxkbvk","value": 56},
{"geohash": "sxk9rw","value": 54},
{"geohash": "sxkds2","value": 100},
{"geohash": "sxm40w","value": 80},
{"geohash": "sxk3jd","value": 25},
{"geohash": "sx7cmw","value": 80},
{"geohash": "sxk6dm","value": 61},
{"geohash": "sxk3js","value": 22},
{"geohash": "sxk3hy","value": 58},
{"geohash": "sxk990","value": 23},
{"geohash": "sxk981","value": 18},
{"geohash": "sxk3ph","value": 19},
{"geohash": "sxk9p2","value": 20},
{"geohash": "sxk9u8","value": 50},
{"geohash": "sxk90e","value": 52},
{"geohash": "sxk3em","value": 30},
{"geohash": "sxk9dq","value": 27},
{"geohash": "sxk3ry","value": 17},
{"geohash": "sxk9pn","value": 33},
{"geohash": "sx7cu3","value": 76},
{"geohash": "sxk9mh","value": 28},
{"geohash": "sxk8zq","value": 48},
{"geohash": "sxk9ew","value": 15},
{"geohash": "sxk9mf","value": 18},
{"geohash": "sxk1rn","value": 55},
{"geohash": "sxk1u6","value": 90},
{"geohash": "sxkbg2","value": 61},
{"geohash": "sxk9md","value": 16},
{"geohash": "sxkc0v","value": 26},
{"geohash": "sxk9gk","value": 46},
{"geohash": "sxkbe7","value": 52},
{"geohash": "sxk930","value": 21},
{"geohash": "sxk6xs","value": 33},
{"geohash": "sxk3m4","value": 19},
{"geohash": "sxk9be","value": 43},
{"geohash": "sxk8ys","value": 33},
{"geohash": "sxk1dq","value": 73},
{"geohash": "sxk9f3","value": 56},
{"geohash": "sxk90z","value": 38},
{"geohash": "sxk6mg","value": 29},
{"geohash": "sxk1w7","value": 97},
{"geohash": "sxk9j7","value": 22},
{"geohash": "sxk3jt","value": 29},
{"geohash": "sxkc9b","value": 76},
{"geohash": "sxk3rb","value": 16},
{"geohash": "sxkcft","value": 55},
{"geohash": "sxk3c6","value": 84},
{"geohash": "sxkb8j","value": 22},
{"geohash": "sxk9mb","value": 19},
{"geohash": "sxkcd9","value": 81},
{"geohash": "sxk9p5","value": 21},
{"geohash": "sx7cmj","value": 93},
{"geohash": "sxkc17","value": 53},
{"geohash": "sxk3p6","value": 42},
{"geohash": "sx7cx5","value": 151},
{"geohash": "sxk6nq","value": 65},
{"geohash": "sxk3p4","value": 40},
{"geohash": "sxkbsb","value": 71},
{"geohash": "sxk924","value": 18},
{"geohash": "sxk93m","value": 24},
{"geohash": "sxk9d4","value": 19},
{"geohash": "sx7frd","value": 80},
{"geohash": "sxk9tj","value": 36},
{"geohash": "sxk9m4","value": 31},
{"geohash": "sxk3jh","value": 30},
{"geohash": "sx7ghk","value": 45},
{"geohash": "sxkdh4","value": 52},
{"geohash": "sxk9s6","value": 19},
{"geohash": "sxk9qm","value": 26},
{"geohash": "sxk6x5","value": 90},
{"geohash": "sxkbvf","value": 116},
{"geohash": "sxk3tk","value": 25},
{"geohash": "sxk9m9","value": 21},
{"geohash": "sxk9sw","value": 22},
{"geohash": "sxk3pm","value": 27},
{"geohash": "sxk3rs","value": 23},
{"geohash": "sxk9qd","value": 24},
{"geohash": "sxkc06","value": 29},
{"geohash": "sxk96r","value": 27},
{"geohash": "sxk926","value": 21},
{"geohash": "sxkfpw","value": 75},
{"geohash": "sxk9nf","value": 19},
{"geohash": "sxk90m","value": 21},
{"geohash": "sxk6qv","value": 37},
{"geohash": "sxk9td","value": 19},
{"geohash": "sxkd42","value": 68},
{"geohash": "sxk6me","value": 26},
{"geohash": "sxk33w","value": 55},
{"geohash": "sxk3gk","value": 34},
{"geohash": "sxkc2u","value": 60},
{"geohash": "sxkc3s","value": 66},
{"geohash": "sxk9zq","value": 60},
{"geohash": "sxk9r7","value": 21},
{"geohash": "sxk3ww","value": 30},
{"geohash": "sxk66x","value": 94},
{"geohash": "sxk9cd","value": 16},
{"geohash": "sxk1cy","value": 56},
{"geohash": "sxk91k","value": 44},
{"geohash": "sxk3g2","value": 90},
{"geohash": "sxk9uf","value": 46},
{"geohash": "sxk3r6","value": 20},
{"geohash": "sxkc82","value": 42},
{"geohash": "sxkbk2","value": 81},
{"geohash": "sxkbe8","value": 43},
{"geohash": "sxk9sn","value": 20},
{"geohash": "sxk69f","value": 90},
{"geohash": "sxk9q7","value": 20},
{"geohash": "sxkbkx","value": 69},
{"geohash": "sxk9pj","value": 28},
{"geohash": "sxkcd5","value": 104},
{"geohash": "sxk9ss","value": 28},
{"geohash": "sxkfpj","value": 71},
{"geohash": "sxk6ru","value": 86},
{"geohash": "sx7cx4","value": 83},
{"geohash": "sxk67h","value": 54},
{"geohash": "sx7fvq","value": 66},
{"geohash": "sxkc83","value": 102},
{"geohash": "sxk40k","value": 92},
{"geohash": "sxm41h","value": 92},
{"geohash": "sxkc62","value": 99},
{"geohash": "sxk93y","value": 31},
{"geohash": "sxkbgx","value": 81},
{"geohash": "sxkc5m","value": 92},
{"geohash": "sxkcgy","value": 70},
{"geohash": "sxk9vb","value": 30},
{"geohash": "sxk69g","value": 79},
{"geohash": "sxk6e4","value": 93},
{"geohash": "sxkbg4","value": 31},
{"geohash": "sxk92s","value": 15},
{"geohash": "sxk3e7","value": 34},
{"geohash": "sxkd2f","value": 85},
{"geohash": "sxk9jj","value": 24},
{"geohash": "sxk9ms","value": 17},
{"geohash": "sxkbsn","value": 78},
{"geohash": "sxk3f5","value": 96},
{"geohash": "sxk93f","value": 33},
{"geohash": "sxk96g","value": 24},
{"geohash": "sxk99x","value": 24},
{"geohash": "sxk97p","value": 36},
{"geohash": "sxkb92","value": 45},
{"geohash": "sxk6g7","value": 79},
{"geohash": "sxk9sv","value": 33},
{"geohash": "sxkdkv","value": 37},
{"geohash": "sx7fvb","value": 69},
{"geohash": "sxk36u","value": 33},
{"geohash": "sxk6p3","value": 66},
{"geohash": "sxk9e1","value": 40},
{"geohash": "sxk936","value": 25},
{"geohash": "sxk6es","value": 92},
{"geohash": "sxk3t5","value": 28},
{"geohash": "sxk9pu","value": 22},
{"geohash": "sxk99d","value": 24},
{"geohash": "sxkc4z","value": 100},
{"geohash": "sxk9fw","value": 66},
{"geohash": "sxkbv7","value": 102},
{"geohash": "sx7fqz","value": 96},
{"geohash": "sxkc09","value": 32},
{"geohash": "sxk9j4","value": 23},
{"geohash": "sxk1qz","value": 75},
{"geohash": "sxk4pg","value": 83},
{"geohash": "sx7fvc","value": 79},
{"geohash": "sxkbb3","value": 32},
{"geohash": "sxhzvt","value": 14},
{"geohash": "sxk6xg","value": 68},
{"geohash": "sxkdhj","value": 51},
{"geohash": "sxkd94","value": 95},
{"geohash": "sxk9mc","value": 16},
{"geohash": "sxk9sh","value": 20},
{"geohash": "sxk3qv","value": 22},
{"geohash": "sxk6su","value": 81},
{"geohash": "sxk6mq","value": 49},
{"geohash": "sxkdqk","value": 101},
{"geohash": "sxk8zc","value": 27},
{"geohash": "sxkf0p","value": 66},
{"geohash": "sxkbg8","value": 65},
{"geohash": "sxkdkb","value": 33},
{"geohash": "sxk6np","value": 54},
{"geohash": "sxk3nw","value": 22},
{"geohash": "sxk6d8","value": 33},
{"geohash": "sxkdj4","value": 32},
{"geohash": "sx7ghb","value": 40},
{"geohash": "sxk3yu","value": 47},
{"geohash": "sxk3ku","value": 42},
{"geohash": "sxkbj8","value": 50},
{"geohash": "sxk90w","value": 33},
{"geohash": "sxk45f","value": 67},
{"geohash": "sxk9m8","value": 25},
{"geohash": "sxk9mu","value": 20},
{"geohash": "sxk61n","value": 94},
{"geohash": "sxk917","value": 47},
{"geohash": "sxm44h","value": 74},
{"geohash": "sxk3sd","value": 39},
{"geohash": "sxk4x8","value": 39},
{"geohash": "sxk3xe","value": 40},
{"geohash": "sxkbmk","value": 91},
{"geohash": "sxk40d","value": 97},
{"geohash": "sxk9rk","value": 24},
{"geohash": "sxk98u","value": 56},
{"geohash": "sxk9eg","value": 22},
{"geohash": "sxk9c4","value": 31},
{"geohash": "sxk8xq","value": 59},
{"geohash": "sxk3s4","value": 49},
{"geohash": "sxk18m","value": 81},
{"geohash": "sxk3q8","value": 36},
{"geohash": "sxk9qt","value": 28},
{"geohash": "sxk4jk","value": 93},
{"geohash": "sxk3p9","value": 53},
{"geohash": "sxk3pq","value": 27},
{"geohash": "sxk9vr","value": 40},
{"geohash": "sxk9w4","value": 24},
{"geohash": "sxk6e0","value": 91},
{"geohash": "sxkf44","value": 102},
{"geohash": "sxkb6u","value": 36},
{"geohash": "sxkdh9","value": 27},
{"geohash": "sxk1fu","value": 82},
{"geohash": "sxkc5e","value": 88},
{"geohash": "sxk1tw","value": 92},
{"geohash": "sxk4r2","value": 34},
{"geohash": "sxk1sg","value": 77},
{"geohash": "sx7fwh","value": 88},
{"geohash": "sxk972","value": 32},
{"geohash": "sxk9x2","value": 103},
{"geohash": "sxk1gx","value": 78},
{"geohash": "sxk9k2","value": 36},
{"geohash": "sxk6qs","value": 34},
{"geohash": "sxk9pz","value": 28},
{"geohash": "sxkcf2","value": 98},
{"geohash": "sxk4pq","value": 44},
{"geohash": "sxk9vg","value": 33},
{"geohash": "sxk3wd","value": 51},
{"geohash": "sxk3kw","value": 26},
{"geohash": "sxkdh8","value": 24},
{"geohash": "sxk3ky","value": 34},
{"geohash": "sx7czt","value": 60},
{"geohash": "sxk99j","value": 47},
{"geohash": "sxk9j6","value": 10},
{"geohash": "sxkdhx","value": 32},
{"geohash": "sxkdk4","value": 39},
{"geohash": "sxkb8r","value": 50},
{"geohash": "sxk4rz","value": 71},
{"geohash": "sxkf2v","value": 53},
{"geohash": "sx7fms","value": 90},
{"geohash": "sxkdrg","value": 104},
{"geohash": "sxk6mb","value": 65},
{"geohash": "sxk90k","value": 65},
{"geohash": "sxk6g6","value": 71},
{"geohash": "sxkc44","value": 47},
{"geohash": "sxk69u","value": 68},
{"geohash": "sxkd2r","value": 80},
{"geohash": "sxkdj0","value": 30},
{"geohash": "sxk9m0","value": 34},
{"geohash": "sxk6ts","value": 92},
{"geohash": "sxk91v","value": 56},
{"geohash": "sxk9f2","value": 24},
{"geohash": "sxk9e6","value": 31},
{"geohash": "sxkbb0","value": 46},
{"geohash": "sxkc02","value": 33},
{"geohash": "sxkbgf","value": 45},
{"geohash": "sxk99w","value": 23},
{"geohash": "sxk1tv","value": 86},
{"geohash": "sxk8yx","value": 37},
{"geohash": "sxk3sv","value": 25},
{"geohash": "sxkdt9","value": 103},
{"geohash": "sxk9mk","value": 27},
{"geohash": "sxk6dj","value": 54},
{"geohash": "sx7chx","value": 74},
{"geohash": "sxk3rc","value": 21},
{"geohash": "sxkbs7","value": 88},
{"geohash": "sxk3s8","value": 27},
{"geohash": "sxk9jp","value": 35},
{"geohash": "sxkc3x","value": 111},
{"geohash": "sxkdsb","value": 104},
{"geohash": "sxk1xc","value": 81},
{"geohash": "sxk9e5","value": 34},
{"geohash": "sxkb87","value": 37},
{"geohash": "sxk66k","value": 90},
{"geohash": "sx7cmq","value": 88},
{"geohash": "sxk9bb","value": 35},
{"geohash": "sxk99r","value": 31},
{"geohash": "sxk922","value": 16},
{"geohash": "sxkdpv","value": 66},
{"geohash": "sxk9dw","value": 18},
{"geohash": "sxk9ty","value": 48},
{"geohash": "sxk93d","value": 29},
{"geohash": "sxkc15","value": 56},
{"geohash": "sxk9cb","value": 34},
{"geohash": "sx7cwq","value": 82},
{"geohash": "sxk9rc","value": 21},
{"geohash": "sxk9g4","value": 57},
{"geohash": "sxk9nh","value": 27},
{"geohash": "sxk3qc","value": 19},
{"geohash": "sxk99t","value": 15},
{"geohash": "sxk1ry","value": 76},
{"geohash": "sxk3ke","value": 57},
{"geohash": "sxk3bn","value": 54},
{"geohash": "sxk8ye","value": 52},
{"geohash": "sxkcun","value": 68},
{"geohash": "sxm41u","value": 68},
{"geohash": "sxkdqg","value": 105},
{"geohash": "sxk9sq","value": 20},
{"geohash": "sxk9d8","value": 21},
{"geohash": "sx7fw6","value": 85},
{"geohash": "sxkbff","value": 29},
{"geohash": "sxk9n5","value": 26},
{"geohash": "sxk6xe","value": 61},
{"geohash": "sx7fr0","value": 56},
{"geohash": "sxkc84","value": 106},
{"geohash": "sxkcdh","value": 102},
{"geohash": "sxkdk3","value": 31},
{"geohash": "sxk9sk","value": 23},
{"geohash": "sxk9nt","value": 28},
{"geohash": "sxk6p9","value": 88},
{"geohash": "sxk3br","value": 96},
{"geohash": "sxk9vd","value": 54},
{"geohash": "sxkcfq","value": 93},
{"geohash": "sxk3ez","value": 35},
{"geohash": "sxkc81","value": 106},
{"geohash": "sxk6ph","value": 37},
{"geohash": "sxkcvs","value": 69},
{"geohash": "sxkdn9","value": 40},
{"geohash": "sxkde8","value": 92},
{"geohash": "sxkd9d","value": 92},
{"geohash": "sxk96w","value": 24},
{"geohash": "sxk1s5","value": 80},
{"geohash": "sxk98q","value": 68},
{"geohash": "sxk3gc","value": 39},
{"geohash": "sxk3w7","value": 51},
{"geohash": "sxk9eq","value": 21},
{"geohash": "sxk9qw","value": 32},
{"geohash": "sxkbg7","value": 32},
{"geohash": "sxk699","value": 84},
{"geohash": "sxk4r8","value": 80},
{"geohash": "sxk3ws","value": 43},
{"geohash": "sxk9rq","value": 63},
{"geohash": "sxk3hd","value": 35},
{"geohash": "sx7fmk","value": 90},
{"geohash": "sxk3cg","value": 94},
{"geohash": "sxk3p5","value": 27},
{"geohash": "sxk3r8","value": 34},
{"geohash": "sxk9ex","value": 20},
{"geohash": "sxk9rg","value": 30},
{"geohash": "sxk9dr","value": 22},
{"geohash": "sxk9r0","value": 22},
{"geohash": "sxkdkx","value": 33},
{"geohash": "sxk3r0","value": 16},
{"geohash": "sxk1g4","value": 49},
{"geohash": "sxk9rn","value": 60},
{"geohash": "sxk9ds","value": 20},
{"geohash": "sxk69d","value": 81},
{"geohash": "sxkd2n","value": 60},
{"geohash": "sxkdpd","value": 91},
{"geohash": "sxkc43","value": 32},
{"geohash": "sxk4rw","value": 95},
{"geohash": "sxk1rs","value": 70},
{"geohash": "sxk66h","value": 86},
{"geohash": "sxk3ge","value": 52},
{"geohash": "sxkc2d","value": 46},
{"geohash": "sxkcut","value": 73},
{"geohash": "sxk6mu","value": 33},
{"geohash": "sxk40m","value": 109},
{"geohash": "sxk3j5","value": 26},
{"geohash": "sxk3sj","value": 31},
{"geohash": "sxk9tu","value": 25},
{"geohash": "sxk6kc","value": 50},
{"geohash": "sxkb8z","value": 54},
{"geohash": "sxkbfw","value": 29},
{"geohash": "sx7fqy","value": 86},
{"geohash": "sxk6tj","value": 66},
{"geohash": "sxk1rm","value": 72},
{"geohash": "sxkf2d","value": 94},
{"geohash": "sxk6gf","value": 75},
{"geohash": "sxk9v6","value": 34},
{"geohash": "sxkf46","value": 92},
{"geohash": "sxkcus","value": 86},
{"geohash": "sxk1bd","value": 84},
{"geohash": "sxk1v2","value": 96},
{"geohash": "sxk9qv","value": 34},
{"geohash": "sxkc0s","value": 63},
{"geohash": "sxk4j5","value": 102},
{"geohash": "sxk9s2","value": 26},
{"geohash": "sxkbvh","value": 87},
{"geohash": "sxkfn0","value": 76},
{"geohash": "sxkdhe","value": 29},
{"geohash": "sxk3tf","value": 39},
{"geohash": "sxk9kx","value": 27},
{"geohash": "sxkd9f","value": 101},
{"geohash": "sxk3kz","value": 30},
{"geohash": "sxk9f8","value": 30},
{"geohash": "sxk37k","value": 23},
{"geohash": "sxk9s4","value": 19},
{"geohash": "sxk1rq","value": 76},
{"geohash": "sxk9r5","value": 20},
{"geohash": "sxk37c","value": 57},
{"geohash": "sxkcd0","value": 96},
{"geohash": "sxk9ru","value": 38},
{"geohash": "sxk9tn","value": 35},
{"geohash": "sxkbg6","value": 42},
{"geohash": "sxk33g","value": 41},
{"geohash": "sxkdnb","value": 70},
{"geohash": "sxkbmp","value": 86},
{"geohash": "sxk3ju","value": 28},
{"geohash": "sxkc23","value": 20},
{"geohash": "sxkf23","value": 69},
{"geohash": "sxkd2u","value": 94},
{"geohash": "sxk4pe","value": 35},
{"geohash": "sxk99m","value": 21},
{"geohash": "sxk92g","value": 18},
{"geohash": "sxk9px","value": 35},
{"geohash": "sxkbgp","value": 51},
{"geohash": "sxkcfs","value": 81},
{"geohash": "sxk94r","value": 64},
{"geohash": "sxk97x","value": 23},
{"geohash": "sxk6xh","value": 94},
{"geohash": "sxkc0g","value": 40},
{"geohash": "sxk61x","value": 99},
{"geohash": "sxkd7c","value": 34},
{"geohash": "sxk99e","value": 20},
{"geohash": "sxk9bq","value": 76},
{"geohash": "sxk9bm","value": 61},
{"geohash": "sxkdr5","value": 106},
{"geohash": "sxk1dt","value": 45},
{"geohash": "sxk9wj","value": 46},
{"geohash": "sxk4pd","value": 31},
{"geohash": "sxk9v8","value": 49},
{"geohash": "sxk1qx","value": 59},
{"geohash": "sxk66v","value": 60},
{"geohash": "sxkc88","value": 107},
{"geohash": "sxkb8q","value": 18},
{"geohash": "sxk9tt","value": 27},
{"geohash": "sxkd4c","value": 46},
{"geohash": "sxk9wk","value": 48},
{"geohash": "sxkf1x","value": 104},
{"geohash": "sxk6gd","value": 71},
{"geohash": "sxk9qu","value": 28},
{"geohash": "sxk682","value": 96},
{"geohash": "sxkc1c","value": 30},
{"geohash": "sxkbhm","value": 72},
{"geohash": "sxk975","value": 22},
{"geohash": "sxk3xq","value": 38},
{"geohash": "sxk9qj","value": 21},
{"geohash": "sxk9np","value": 18},
{"geohash": "sxkc0c","value": 48},
{"geohash": "sxk1xb","value": 56},
{"geohash": "sxkc1d","value": 48},
{"geohash": "sxkde9","value": 85},
{"geohash": "sxk9t2","value": 23},
{"geohash": "sxk3j6","value": 28},
{"geohash": "sxkcfe","value": 98},
{"geohash": "sxk1cw","value": 77},
{"geohash": "sxk9q5","value": 21},
{"geohash": "sxk9jc","value": 20},
{"geohash": "sxk4jy","value": 83},
{"geohash": "sxkb9b","value": 35},
{"geohash": "sxk8xt","value": 48},
{"geohash": "sxk9c5","value": 29},
{"geohash": "sxk6fc","value": 77},
{"geohash": "sxk9jt","value": 18},
{"geohash": "sxk1w2","value": 81},
{"geohash": "sxkdt8","value": 106},
{"geohash": "sxk980","value": 18},
{"geohash": "sxk9ky","value": 25},
{"geohash": "sxkbe3","value": 26},
{"geohash": "sxk373","value": 21},
{"geohash": "sx7fqs","value": 91},
{"geohash": "sxk928","value": 14},
{"geohash": "sxkb7q","value": 44},
{"geohash": "sxk6e6","value": 94},
{"geohash": "sxk3xh","value": 33},
{"geohash": "sxk1se","value": 75},
{"geohash": "sxk38e","value": 95},
{"geohash": "sxk9kh","value": 30},
{"geohash": "sxkc22","value": 20},
{"geohash": "sxkdk5","value": 44},
{"geohash": "sxk4pw","value": 82},
{"geohash": "sxkb8p","value": 35},
{"geohash": "sxkc65","value": 99},
{"geohash": "sxkbgt","value": 79},
{"geohash": "sxk8vz","value": 50},
{"geohash": "sx7fvd","value": 73},
{"geohash": "sxk9fg","value": 37},
{"geohash": "sxk61j","value": 95},
{"geohash": "sxk323","value": 79},
{"geohash": "sxkf1t","value": 97},
{"geohash": "sxk3ss","value": 21},
{"geohash": "sxk4rd","value": 90},
{"geohash": "sxk1eu","value": 74},
{"geohash": "sxk9uw","value": 31},
{"geohash": "sxk9uc","value": 50},
{"geohash": "sxk9kp","value": 20},
{"geohash": "sxk3ek","value": 32},
{"geohash": "sxk3m0","value": 20},
{"geohash": "sxk4hd","value": 90},
{"geohash": "sxk1cm","value": 91},
{"geohash": "sxkc69","value": 85},
{"geohash": "sxk38z","value": 56},
{"geohash": "sxk9jk","value": 21},
{"geohash": "sxk1zz","value": 39},
{"geohash": "sxk8yr","value": 27},
{"geohash": "sxk9hg","value": 26},
{"geohash": "sxk3w6","value": 42},
{"geohash": "sxk9v5","value": 31},
{"geohash": "sxk9ju","value": 17},
{"geohash": "sx7cv1","value": 59},
{"geohash": "sxk98v","value": 74},
{"geohash": "sxk9b3","value": 66},
{"geohash": "sxkb6t","value": 42},
{"geohash": "sxk90g","value": 43},
{"geohash": "sxkbvg","value": 113},
{"geohash": "sxk39h","value": 86},
{"geohash": "sxk3x9","value": 31},
{"geohash": "sxk9w7","value": 55},
{"geohash": "sxk9gu","value": 23},
{"geohash": "sx7fqk","value": 78},
{"geohash": "sxk3sn","value": 53},
{"geohash": "sxkb8e","value": 33},
{"geohash": "sxk398","value": 80},
{"geohash": "sxk3kx","value": 24},
{"geohash": "sxk3nx","value": 17},
{"geohash": "sxk1cq","value": 81},
{"geohash": "sxk9vt","value": 16},
{"geohash": "sxk3ey","value": 93},
{"geohash": "sxk1w6","value": 82},
{"geohash": "sxkdk6","value": 51},
{"geohash": "sxk3xd","value": 26},
{"geohash": "sxk8vx","value": 52},
{"geohash": "sxhzvr","value": 70},
{"geohash": "sxkdk1","value": 40},
{"geohash": "sxk9ch","value": 47},
{"geohash": "sxk9p4","value": 21},
{"geohash": "sxk9ek","value": 23},
{"geohash": "sxkbuh","value": 76},
{"geohash": "sxk9pg","value": 30},
{"geohash": "sxk9s8","value": 30},
{"geohash": "sxk9s3","value": 25},
{"geohash": "sxk66m","value": 90},
{"geohash": "sxk9dz","value": 20},
{"geohash": "sxk9r6","value": 22},
{"geohash": "sxk409","value": 91},
{"geohash": "sxk3nz","value": 18},
{"geohash": "sxkdt3","value": 102},
{"geohash": "sxk999","value": 18},
{"geohash": "sxkdkd","value": 33},
{"geohash": "sxk33d","value": 45},
{"geohash": "sxk1rt","value": 60},
{"geohash": "sxk3bp","value": 48},
{"geohash": "sxk3xr","value": 34},
{"geohash": "sxk96y","value": 20},
{"geohash": "sxk45c","value": 90},
{"geohash": "sxk9we","value": 56},
{"geohash": "sxk6p8","value": 53},
{"geohash": "sxk4h6","value": 86},
{"geohash": "sxk6sv","value": 72},
{"geohash": "sxk9q8","value": 40},
{"geohash": "sxkd34","value": 38},
{"geohash": "sxkb85","value": 35},
{"geohash": "sxk9yz","value": 73},
{"geohash": "sxk1bg","value": 72},
{"geohash": "sxkbsc","value": 86},
{"geohash": "sxk9dh","value": 37},
{"geohash": "sxk6t4","value": 60},
{"geohash": "sxk3t9","value": 37},
{"geohash": "sxkbb2","value": 19},
{"geohash": "sx7cwp","value": 79},
{"geohash": "sxk3xn","value": 30}
]